Workbook

Sheet Instructions
A1: How to Use This Bill Calendar
A4: 1. Open 'Setup' first. Confirm your bill categories and payment methods.
A5: 2. Log every recurring bill in 'Bill Tracker' — Amount, Frequency (Monthly, Quarterly, Annually, or One-Time), Due Day (day of the month, 1-31), Start Date, and optional End Date.
A6: 3. For One-Time bills, the Start Date's day is used automatically — the Due Day field is ignored for those rows.
A7: 4. Change the Year/Month at the top of 'Bill Calendar' to see that month's due bills laid out on a visual calendar grid, with total amount due per day.
A8: 5. Rows in 'Bill Tracker' highlight automatically when a bill is due in the month currently selected on 'Bill Calendar' — orange if it also needs manual payment (Auto-Pay = No).
A9: 6. Only edit yellow (input) or white cells. Green-header and formula/helper cells (columns K onward in Bill Tracker) update automatically — do not overwrite them.
A11: Prepared for {{CLIENT_NAME}} ({{NICHE}}). Amounts are in {{CURRENCY}}.

Sheet Setup
A1: {{CLIENT_NAME}} — Setup
A2: {{NICHE}} — configure once, everything else updates automatically
A3: Bill Categories | B3: Payment Methods
A4: Rent/Mortgage | B4: Bank Transfer
A5: Utilities | B5: Credit Card
A6: Software & Subscriptions | B6: Debit Card
A7: Insurance | B7: PayPal
A8: Loan Payment | B8: Cash
A9: Marketing | B9: Other
A10: Supplies
A11: Other

Sheet Bill Tracker
A1: {{CLIENT_NAME}} — Bill Tracker
A2: Bill Name | B2: Category | C2: Amount ({{CURRENCY}}) | D2: Frequency | E2: Due Day (1-31) | F2: Start Date | G2: End Date (blank = ongoing) | H2: Payment Method | I2: Auto-Pay | J2: Status | K2: Start Idx | L2: End Idx | M2: Selected Idx | N2: In Range? | O2: Frequency Match? | P2: Due This Month? | Q2: Due Day This Month | R2: Due Date This Month
K3: =IF(A3="","",YEAR(F3)*12+MONTH(F3)) | L3: =IF(A3="","",IF(G3="",999999,YEAR(G3)*12+MONTH(G3))) | M3: =IF(A3="","",'Bill Calendar'!$B$3*12+'Bill Calendar'!$D$3) | N3: =IF(A3="","",AND(M3>=K3,M3<=L3,J3="Active")) | O3: =IF(A3="","",IF(D3="One-Time",M3=K3,IF(D3="Monthly",TRUE(),IF(D3="Quarterly",MOD(M3-K3,3)=0,IF(D3="Annually",MOD(M3-K3,12)=0,FALSE()))))) | P3: =IF(A3="","",AND(N3,O3)) | Q3: =IF(A3="","",IF(D3="One-Time",DAY(F3),MIN(E3,DAY(DATE('Bill Calendar'!$B$3,'Bill Calendar'!$D$3+1,1)-1)))) | R3: =IF(A3="","",IF(P3,DATE('Bill Calendar'!$B$3,'Bill Calendar'!$D$3,Q3),""))
K4: =IF(A4="","",YEAR(F4)*12+MONTH(F4)) | L4: =IF(A4="","",IF(G4="",999999,YEAR(G4)*12+MONTH(G4))) | M4: =IF(A4="","",'Bill Calendar'!$B$3*12+'Bill Calendar'!$D$3) | N4: =IF(A4="","",AND(M4>=K4,M4<=L4,J4="Active")) | O4: =IF(A4="","",IF(D4="One-Time",M4=K4,IF(D4="Monthly",TRUE(),IF(D4="Quarterly",MOD(M4-K4,3)=0,IF(D4="Annually",MOD(M4-K4,12)=0,FALSE()))))) | P4: =IF(A4="","",AND(N4,O4)) | Q4: =IF(A4="","",IF(D4="One-Time",DAY(F4),MIN(E4,DAY(DATE('Bill Calendar'!$B$3,'Bill Calendar'!$D$3+1,1)-1)))) | R4: =IF(A4="","",IF(P4,DATE('Bill Calendar'!$B$3,'Bill Calendar'!$D$3,Q4),""))
K5: =IF(A5="","",YEAR(F5)*12+MONTH(F5)) | L5: =IF(A5="","",IF(G5="",999999,YEAR(G5)*12+MONTH(G5))) | M5: =IF(A5="","",'Bill Calendar'!$B$3*12+'Bill Calendar'!$D$3) | N5: =IF(A5="","",AND(M5>=K5,M5<=L5,J5="Active")) | O5: =IF(A5="","",IF(D5="One-Time",M5=K5,IF(D5="Monthly",TRUE(),IF(D5="Quarterly",MOD(M5-K5,3)=0,IF(D5="Annually",MOD(M5-K5,12)=0,FALSE()))))) | P5: =IF(A5="","",AND(N5,O5)) | Q5: =IF(A5="","",IF(D5="One-Time",DAY(F5),MIN(E5,DAY(DATE('Bill Calendar'!$B$3,'Bill Calendar'!$D$3+1,1)-1)))) | R5: =IF(A5="","",IF(P5,DATE('Bill Calendar'!$B$3,'Bill Calendar'!$D$3,Q5),""))
K6: =IF(A6="","",YEAR(F6)*12+MONTH(F6)) | L6: =IF(A6="","",IF(G6="",999999,YEAR(G6)*12+MONTH(G6))) | M6: =IF(A6="","",'Bill Calendar'!$B$3*12+'Bill Calendar'!$D$3) | N6: =IF(A6="","",AND(M6>=K6,M6<=L6,J6="Active")) | O6: =IF(A6="","",IF(D6="One-Time",M6=K6,IF(D6="Monthly",TRUE(),IF(D6="Quarterly",MOD(M6-K6,3)=0,IF(D6="Annually",MOD(M6-K6,12)=0,FALSE()))))) | P6: =IF(A6="","",AND(N6,O6)) | Q6: =IF(A6="","",IF(D6="One-Time",DAY(F6),MIN(E6,DAY(DATE('Bill Calendar'!$B$3,'Bill Calendar'!$D$3+1,1)-1)))) | R6: =IF(A6="","",IF(P6,DATE('Bill Calendar'!$B$3,'Bill Calendar'!$D$3,Q6),""))
K7: =IF(A7="","",YEAR(F7)*12+MONTH(F7)) | L7: =IF(A7="","",IF(G7="",999999,YEAR(G7)*12+MONTH(G7))) | M7: =IF(A7="","",'Bill Calendar'!$B$3*12+'Bill Calendar'!$D$3) | N7: =IF(A7="","",AND(M7>=K7,M7<=L7,J7="Active")) | O7: =IF(A7="","",IF(D7="One-Time",M7=K7,IF(D7="Monthly",TRUE(),IF(D7="Quarterly",MOD(M7-K7,3)=0,IF(D7="Annually",MOD(M7-K7,12)=0,FALSE()))))) | P7: =IF(A7="","",AND(N7,O7)) | Q7: =IF(A7="","",IF(D7="One-Time",DAY(F7),MIN(E7,DAY(DATE('Bill Calendar'!$B$3,'Bill Calendar'!$D$3+1,1)-1)))) | R7: =IF(A7="","",IF(P7,DATE('Bill Calendar'!$B$3,'Bill Calendar'!$D$3,Q7),""))
K8: =IF(A8="","",YEAR(F8)*12+MONTH(F8)) | L8: =IF(A8="","",IF(G8="",999999,YEAR(G8)*12+MONTH(G8))) | M8: =IF(A8="","",'Bill Calendar'!$B$3*12+'Bill Calendar'!$D$3) | N8: =IF(A8="","",AND(M8>=K8,M8<=L8,J8="Active")) | O8: =IF(A8="","",IF(D8="One-Time",M8=K8,IF(D8="Monthly",TRUE(),IF(D8="Quarterly",MOD(M8-K8,3)=0,IF(D8="Annually",MOD(M8-K8,12)=0,FALSE()))))) | P8: =IF(A8="","",AND(N8,O8)) | Q8: =IF(A8="","",IF(D8="One-Time",DAY(F8),MIN(E8,DAY(DATE('Bill Calendar'!$B$3,'Bill Calendar'!$D$3+1,1)-1)))) | R8: =IF(A8="","",IF(P8,DATE('Bill Calendar'!$B$3,'Bill Calendar'!$D$3,Q8),""))
K9: =IF(A9="","",YEAR(F9)*12+MONTH(F9)) | L9: =IF(A9="","",IF(G9="",999999,YEAR(G9)*12+MONTH(G9))) | M9: =IF(A9="","",'Bill Calendar'!$B$3*12+'Bill Calendar'!$D$3) | N9: =IF(A9="","",AND(M9>=K9,M9<=L9,J9="Active")) | O9: =IF(A9="","",IF(D9="One-Time",M9=K9,IF(D9="Monthly",TRUE(),IF(D9="Quarterly",MOD(M9-K9,3)=0,IF(D9="Annually",MOD(M9-K9,12)=0,FALSE()))))) | P9: =IF(A9="","",AND(N9,O9)) | Q9: =IF(A9="","",IF(D9="One-Time",DAY(F9),MIN(E9,DAY(DATE('Bill Calendar'!$B$3,'Bill Calendar'!$D$3+1,1)-1)))) | R9: =IF(A9="","",IF(P9,DATE('Bill Calendar'!$B$3,'Bill Calendar'!$D$3,Q9),""))
K10: =IF(A10="","",YEAR(F10)*12+MONTH(F10)) | L10: =IF(A10="","",IF(G10="",999999,YEAR(G10)*12+MONTH(G10))) | M10: =IF(A10="","",'Bill Calendar'!$B$3*12+'Bill Calendar'!$D$3) | N10: =IF(A10="","",AND(M10>=K10,M10<=L10,J10="Active")) | O10: =IF(A10="","",IF(D10="One-Time",M10=K10,IF(D10="Monthly",TRUE(),IF(D10="Quarterly",MOD(M10-K10,3)=0,IF(D10="Annually",MOD(M10-K10,12)=0,FALSE()))))) | P10: =IF(A10="","",AND(N10,O10)) | Q10: =IF(A10="","",IF(D10="One-Time",DAY(F10),MIN(E10,DAY(DATE('Bill Calendar'!$B$3,'Bill Calendar'!$D$3+1,1)-1)))) | R10: =IF(A10="","",IF(P10,DATE('Bill Calendar'!$B$3,'Bill Calendar'!$D$3,Q10),""))
K11: =IF(A11="","",YEAR(F11)*12+MONTH(F11)) | L11: =IF(A11="","",IF(G11="",999999,YEAR(G11)*12+MONTH(G11))) | M11: =IF(A11="","",'Bill Calendar'!$B$3*12+'Bill Calendar'!$D$3) | N11: =IF(A11="","",AND(M11>=K11,M11<=L11,J11="Active")) | O11: =IF(A11="","",IF(D11="One-Time",M11=K11,IF(D11="Monthly",TRUE(),IF(D11="Quarterly",MOD(M11-K11,3)=0,IF(D11="Annually",MOD(M11-K11,12)=0,FALSE()))))) | P11: =IF(A11="","",AND(N11,O11)) | Q11: =IF(A11="","",IF(D11="One-Time",DAY(F11),MIN(E11,DAY(DATE('Bill Calendar'!$B$3,'Bill Calendar'!$D$3+1,1)-1)))) | R11: =IF(A11="","",IF(P11,DATE('Bill Calendar'!$B$3,'Bill Calendar'!$D$3,Q11),""))
K12: =IF(A12="","",YEAR(F12)*12+MONTH(F12)) | L12: =IF(A12="","",IF(G12="",999999,YEAR(G12)*12+MONTH(G12))) | M12: =IF(A12="","",'Bill Calendar'!$B$3*12+'Bill Calendar'!$D$3) | N12: =IF(A12="","",AND(M12>=K12,M12<=L12,J12="Active")) | O12: =IF(A12="","",IF(D12="One-Time",M12=K12,IF(D12="Monthly",TRUE(),IF(D12="Quarterly",MOD(M12-K12,3)=0,IF(D12="Annually",MOD(M12-K12,12)=0,FALSE()))))) | P12: =IF(A12="","",AND(N12,O12)) | Q12: =IF(A12="","",IF(D12="One-Time",DAY(F12),MIN(E12,DAY(DATE('Bill Calendar'!$B$3,'Bill Calendar'!$D$3+1,1)-1)))) | R12: =IF(A12="","",IF(P12,DATE('Bill Calendar'!$B$3,'Bill Calendar'!$D$3,Q12),""))
K13: =IF(A13="","",YEAR(F13)*12+MONTH(F13)) | L13: =IF(A13="","",IF(G13="",999999,YEAR(G13)*12+MONTH(G13))) | M13: =IF(A13="","",'Bill Calendar'!$B$3*12+'Bill Calendar'!$D$3) | N13: =IF(A13="","",AND(M13>=K13,M13<=L13,J13="Active")) | O13: =IF(A13="","",IF(D13="One-Time",M13=K13,IF(D13="Monthly",TRUE(),IF(D13="Quarterly",MOD(M13-K13,3)=0,IF(D13="Annually",MOD(M13-K13,12)=0,FALSE()))))) | P13: =IF(A13="","",AND(N13,O13)) | Q13: =IF(A13="","",IF(D13="One-Time",DAY(F13),MIN(E13,DAY(DATE('Bill Calendar'!$B$3,'Bill Calendar'!$D$3+1,1)-1)))) | R13: =IF(A13="","",IF(P13,DATE('Bill Calendar'!$B$3,'Bill Calendar'!$D$3,Q13),""))
K14: =IF(A14="","",YEAR(F14)*12+MONTH(F14)) | L14: =IF(A14="","",IF(G14="",999999,YEAR(G14)*12+MONTH(G14))) | M14: =IF(A14="","",'Bill Calendar'!$B$3*12+'Bill Calendar'!$D$3) | N14: =IF(A14="","",AND(M14>=K14,M14<=L14,J14="Active")) | O14: =IF(A14="","",IF(D14="One-Time",M14=K14,IF(D14="Monthly",TRUE(),IF(D14="Quarterly",MOD(M14-K14,3)=0,IF(D14="Annually",MOD(M14-K14,12)=0,FALSE()))))) | P14: =IF(A14="","",AND(N14,O14)) | Q14: =IF(A14="","",IF(D14="One-Time",DAY(F14),MIN(E14,DAY(DATE('Bill Calendar'!$B$3,'Bill Calendar'!$D$3+1,1)-1)))) | R14: =IF(A14="","",IF(P14,DATE('Bill Calendar'!$B$3,'Bill Calendar'!$D$3,Q14),""))
... K52: =IF(A52="","",YEAR(F52)*12+MONTH(F52)) | L52: =IF(A52="","",IF(G52="",999999,YEAR(G52)*12+MONTH(G52))) | M52: =IF(A52="","",'Bill Calendar'!$B$3*12+'Bill Calendar'!$D$3) | N52: =IF(A52="","",AND(M52>=K52,M52<=L52,J52="Active")) | O52: =IF(A52="","",IF(D52="One-Time",M52=K52,IF(D52="Monthly",TRUE(),IF(D52="Quarterly",MOD(M52-K52,3)=0,IF(D52="Annually",MOD(M52-K52,12)=0,FALSE()))))) | P52: =IF(A52="","",AND(N52,O52)) | Q52: =IF(A52="","",IF(D52="One-Time",DAY(F52),MIN(E52,DAY(DATE('Bill Calendar'!$B$3,'Bill Calendar'!$D$3+1,1)-1)))) | R52: =IF(A52="","",IF(P52,DATE('Bill Calendar'!$B$3,'Bill Calendar'!$D$3,Q52),""))

Sheet Bill Calendar
A1: {{CLIENT_NAME}} — Bill Calendar
A2: {{NICHE}} — figures in {{CURRENCY}}
A3: Year | B3: 2026 | C3: Month | D3: 1
A5: Total Due This Month ({{CURRENCY}}) | B5: Bills Due This Month | C5: Auto-Paid | D5: Needs Manual Payment | F5: Spending by Category — Selected Month
A6: =SUMIFS('Bill Tracker'!$C$3:$C$52,'Bill Tracker'!$P$3:$P$52,TRUE()) -> 0 | B6: =COUNTIF('Bill Tracker'!$P$3:$P$52,TRUE()) -> 0 | C6: =COUNTIFS('Bill Tracker'!$P$3:$P$52,TRUE(),'Bill Tracker'!$I$3:$I$52,"Yes") -> 0 | D6: =COUNTIFS('Bill Tracker'!$P$3:$P$52,TRUE(),'Bill Tracker'!$I$3:$I$52,"No") -> 0 | F6: Category | G6: Amount
F7: Rent/Mortgage | G7: =SUMIFS('Bill Tracker'!$C$3:$C$52,'Bill Tracker'!$B$3:$B$52,"Rent/Mortgage",'Bill Tracker'!$P$3:$P$52,TRUE()) -> 0
F8: Utilities | G8: =SUMIFS('Bill Tracker'!$C$3:$C$52,'Bill Tracker'!$B$3:$B$52,"Utilities",'Bill Tracker'!$P$3:$P$52,TRUE()) -> 0
F9: Software & Subscriptions | G9: =SUMIFS('Bill Tracker'!$C$3:$C$52,'Bill Tracker'!$B$3:$B$52,"Software & Subscriptions",'Bill Tracker'!$P$3:$P$52,TRUE()) -> 0
F10: Insurance | G10: =SUMIFS('Bill Tracker'!$C$3:$C$52,'Bill Tracker'!$B$3:$B$52,"Insurance",'Bill Tracker'!$P$3:$P$52,TRUE()) -> 0
F11: Loan Payment | G11: =SUMIFS('Bill Tracker'!$C$3:$C$52,'Bill Tracker'!$B$3:$B$52,"Loan Payment",'Bill Tracker'!$P$3:$P$52,TRUE()) -> 0
F12: Marketing | G12: =SUMIFS('Bill Tracker'!$C$3:$C$52,'Bill Tracker'!$B$3:$B$52,"Marketing",'Bill Tracker'!$P$3:$P$52,TRUE()) -> 0
F13: Supplies | G13: =SUMIFS('Bill Tracker'!$C$3:$C$52,'Bill Tracker'!$B$3:$B$52,"Supplies",'Bill Tracker'!$P$3:$P$52,TRUE()) -> 0
F14: Other | G14: =SUMIFS('Bill Tracker'!$C$3:$C$52,'Bill Tracker'!$B$3:$B$52,"Other",'Bill Tracker'!$P$3:$P$52,TRUE()) -> 0
A16: Amounts shown in {{CURRENCY}}. Each day's total appears below its date.
A17: Sun | B17: Mon | C17: Tue | D17: Wed | E17: Thu | F17: Fri | G17: Sat
A18: =IF(MONTH((DATE($B$3,$D$3,1)-(WEEKDAY(DATE($B$3,$D$3,1))-1)+0))<>$D$3,"",DAY((DATE($B$3,$D$3,1)-(WEEKDAY(DATE($B$3,$D$3,1))-1)+0))) | B18: =IF(MONTH((DATE($B$3,$D$3,1)-(WEEKDAY(DATE($B$3,$D$3,1))-1)+1))<>$D$3,"",DAY((DATE($B$3,$D$3,1)-(WEEKDAY(DATE($B$3,$D$3,1))-1)+1))) | C18: =IF(MONTH((DATE($B$3,$D$3,1)-(WEEKDAY(DATE($B$3,$D$3,1))-1)+2))<>$D$3,"",DAY((DATE($B$3,$D$3,1)-(WEEKDAY(DATE($B$3,$D$3,1))-1)+2))) | D18: =IF(MONTH((DATE($B$3,$D$3,1)-(WEEKDAY(DATE($B$3,$D$3,1))-1)+3))<>$D$3,"",DAY((DATE($B$3,$D$3,1)-(WEEKDAY(DATE($B$3,$D$3,1))-1)+3))) | E18: =IF(MONTH((DATE($B$3,$D$3,1)-(WEEKDAY(DATE($B$3,$D$3,1))-1)+4))<>$D$3,"",DAY((DATE($B$3,$D$3,1)-(WEEKDAY(DATE($B$3,$D$3,1))-1)+4))) -> 1 | F18: =IF(MONTH((DATE($B$3,$D$3,1)-(WEEKDAY(DATE($B$3,$D$3,1))-1)+5))<>$D$3,"",DAY((DATE($B$3,$D$3,1)-(WEEKDAY(DATE($B$3,$D$3,1))-1)+5))) -> 2 | G18: =IF(MONTH((DATE($B$3,$D$3,1)-(WEEKDAY(DATE($B$3,$D$3,1))-1)+6))<>$D$3,"",DAY((DATE($B$3,$D$3,1)-(WEEKDAY(DATE($B$3,$D$3,1))-1)+6))) -> 3
A19: =IF(MONTH((DATE($B$3,$D$3,1)-(WEEKDAY(DATE($B$3,$D$3,1))-1)+0))<>$D$3,"",SUMIFS('Bill Tracker'!$C$3:$C$52,'Bill Tracker'!$R$3:$R$52,(DATE($B$3,$D$3,1)-(WEEKDAY(DATE($B$3,$D$3,1))-1)+0))) | B19: =IF(MONTH((DATE($B$3,$D$3,1)-(WEEKDAY(DATE($B$3,$D$3,1))-1)+1))<>$D$3,"",SUMIFS('Bill Tracker'!$C$3:$C$52,'Bill Tracker'!$R$3:$R$52,(DATE($B$3,$D$3,1)-(WEEKDAY(DATE($B$3,$D$3,1))-1)+1))) | C19: =IF(MONTH((DATE($B$3,$D$3,1)-(WEEKDAY(DATE($B$3,$D$3,1))-1)+2))<>$D$3,"",SUMIFS('Bill Tracker'!$C$3:$C$52,'Bill Tracker'!$R$3:$R$52,(DATE($B$3,$D$3,1)-(WEEKDAY(DATE($B$3,$D$3,1))-1)+2))) | D19: =IF(MONTH((DATE($B$3,$D$3,1)-(WEEKDAY(DATE($B$3,$D$3,1))-1)+3))<>$D$3,"",SUMIFS('Bill Tracker'!$C$3:$C$52,'Bill Tracker'!$R$3:$R$52,(DATE($B$3,$D$3,1)-(WEEKDAY(DATE($B$3,$D$3,1))-1)+3))) | E19: =IF(MONTH((DATE($B$3,$D$3,1)-(WEEKDAY(DATE($B$3,$D$3,1))-1)+4))<>$D$3,"",SUMIFS('Bill Tracker'!$C$3:$C$52,'Bill Tracker'!$R$3:$R$52,(DATE($B$3,$D$3,1)-(WEEKDAY(DATE($B$3,$D$3,1))-1)+4))) -> 0 | F19: =IF(MONTH((DATE($B$3,$D$3,1)-(WEEKDAY(DATE($B$3,$D$3,1))-1)+5))<>$D$3,"",SUMIFS('Bill Tracker'!$C$3:$C$52,'Bill Tracker'!$R$3:$R$52,(DATE($B$3,$D$3,1)-(WEEKDAY(DATE($B$3,$D$3,1))-1)+5))) -> 0 | G19: =IF(MONTH((DATE($B$3,$D$3,1)-(WEEKDAY(DATE($B$3,$D$3,1))-1)+6))<>$D$3,"",SUMIFS('Bill Tracker'!$C$3:$C$52,'Bill Tracker'!$R$3:$R$52,(DATE($B$3,$D$3,1)-(WEEKDAY(DATE($B$3,$D$3,1))-1)+6))) -> 0
A20: =IF(MONTH((DATE($B$3,$D$3,1)-(WEEKDAY(DATE($B$3,$D$3,1))-1)+7))<>$D$3,"",DAY((DATE($B$3,$D$3,1)-(WEEKDAY(DATE($B$3,$D$3,1))-1)+7))) -> 4 | B20: =IF(MONTH((DATE($B$3,$D$3,1)-(WEEKDAY(DATE($B$3,$D$3,1))-1)+8))<>$D$3,"",DAY((DATE($B$3,$D$3,1)-(WEEKDAY(DATE($B$3,$D$3,1))-1)+8))) -> 5 | C20: =IF(MONTH((DATE($B$3,$D$3,1)-(WEEKDAY(DATE($B$3,$D$3,1))-1)+9))<>$D$3,"",DAY((DATE($B$3,$D$3,1)-(WEEKDAY(DATE($B$3,$D$3,1))-1)+9))) -> 6 | D20: =IF(MONTH((DATE($B$3,$D$3,1)-(WEEKDAY(DATE($B$3,$D$3,1))-1)+10))<>$D$3,"",DAY((DATE($B$3,$D$3,1)-(WEEKDAY(DATE($B$3,$D$3,1))-1)+10))) -> 7 | E20: =IF(MONTH((DATE($B$3,$D$3,1)-(WEEKDAY(DATE($B$3,$D$3,1))-1)+11))<>$D$3,"",DAY((DATE($B$3,$D$3,1)-(WEEKDAY(DATE($B$3,$D$3,1))-1)+11))) -> 8 | F20: =IF(MONTH((DATE($B$3,$D$3,1)-(WEEKDAY(DATE($B$3,$D$3,1))-1)+12))<>$D$3,"",DAY((DATE($B$3,$D$3,1)-(WEEKDAY(DATE($B$3,$D$3,1))-1)+12))) -> 9 | G20: =IF(MONTH((DATE($B$3,$D$3,1)-(WEEKDAY(DATE($B$3,$D$3,1))-1)+13))<>$D$3,"",DAY((DATE($B$3,$D$3,1)-(WEEKDAY(DATE($B$3,$D$3,1))-1)+13))) -> 10
A21: =IF(MONTH((DATE($B$3,$D$3,1)-(WEEKDAY(DATE($B$3,$D$3,1))-1)+7))<>$D$3,"",SUMIFS('Bill Tracker'!$C$3:$C$52,'Bill Tracker'!$R$3:$R$52,(DATE($B$3,$D$3,1)-(WEEKDAY(DATE($B$3,$D$3,1))-1)+7))) -> 0 | B21: =IF(MONTH((DATE($B$3,$D$3,1)-(WEEKDAY(DATE($B$3,$D$3,1))-1)+8))<>$D$3,"",SUMIFS('Bill Tracker'!$C$3:$C$52,'Bill Tracker'!$R$3:$R$52,(DATE($B$3,$D$3,1)-(WEEKDAY(DATE($B$3,$D$3,1))-1)+8))) -> 0 | C21: =IF(MONTH((DATE($B$3,$D$3,1)-(WEEKDAY(DATE($B$3,$D$3,1))-1)+9))<>$D$3,"",SUMIFS('Bill Tracker'!$C$3:$C$52,'Bill Tracker'!$R$3:$R$52,(DATE($B$3,$D$3,1)-(WEEKDAY(DATE($B$3,$D$3,1))-1)+9))) -> 0 | D21: =IF(MONTH((DATE($B$3,$D$3,1)-(WEEKDAY(DATE($B$3,$D$3,1))-1)+10))<>$D$3,"",SUMIFS('Bill Tracker'!$C$3:$C$52,'Bill Tracker'!$R$3:$R$52,(DATE($B$3,$D$3,1)-(WEEKDAY(DATE($B$3,$D$3,1))-1)+10))) -> 0 | E21: =IF(MONTH((DATE($B$3,$D$3,1)-(WEEKDAY(DATE($B$3,$D$3,1))-1)+11))<>$D$3,"",SUMIFS('Bill Tracker'!$C$3:$C$52,'Bill Tracker'!$R$3:$R$52,(DATE($B$3,$D$3,1)-(WEEKDAY(DATE($B$3,$D$3,1))-1)+11))) -> 0 | F21: =IF(MONTH((DATE($B$3,$D$3,1)-(WEEKDAY(DATE($B$3,$D$3,1))-1)+12))<>$D$3,"",SUMIFS('Bill Tracker'!$C$3:$C$52,'Bill Tracker'!$R$3:$R$52,(DATE($B$3,$D$3,1)-(WEEKDAY(DATE($B$3,$D$3,1))-1)+12))) -> 0 | G21: =IF(MONTH((DATE($B$3,$D$3,1)-(WEEKDAY(DATE($B$3,$D$3,1))-1)+13))<>$D$3,"",SUMIFS('Bill Tracker'!$C$3:$C$52,'Bill Tracker'!$R$3:$R$52,(DATE($B$3,$D$3,1)-(WEEKDAY(DATE($B$3,$D$3,1))-1)+13))) -> 0
A22: =IF(MONTH((DATE($B$3,$D$3,1)-(WEEKDAY(DATE($B$3,$D$3,1))-1)+14))<>$D$3,"",DAY((DATE($B$3,$D$3,1)-(WEEKDAY(DATE($B$3,$D$3,1))-1)+14))) -> 11 | B22: =IF(MONTH((DATE($B$3,$D$3,1)-(WEEKDAY(DATE($B$3,$D$3,1))-1)+15))<>$D$3,"",DAY((DATE($B$3,$D$3,1)-(WEEKDAY(DATE($B$3,$D$3,1))-1)+15))) -> 12 | C22: =IF(MONTH((DATE($B$3,$D$3,1)-(WEEKDAY(DATE($B$3,$D$3,1))-1)+16))<>$D$3,"",DAY((DATE($B$3,$D$3,1)-(WEEKDAY(DATE($B$3,$D$3,1))-1)+16))) -> 13 | D22: =IF(MONTH((DATE($B$3,$D$3,1)-(WEEKDAY(DATE($B$3,$D$3,1))-1)+17))<>$D$3,"",DAY((DATE($B$3,$D$3,1)-(WEEKDAY(DATE($B$3,$D$3,1))-1)+17))) -> 14 | E22: =IF(MONTH((DATE($B$3,$D$3,1)-(WEEKDAY(DATE($B$3,$D$3,1))-1)+18))<>$D$3,"",DAY((DATE($B$3,$D$3,1)-(WEEKDAY(DATE($B$3,$D$3,1))-1)+18))) -> 15 | F22: =IF(MONTH((DATE($B$3,$D$3,1)-(WEEKDAY(DATE($B$3,$D$3,1))-1)+19))<>$D$3,"",DAY((DATE($B$3,$D$3,1)-(WEEKDAY(DATE($B$3,$D$3,1))-1)+19))) -> 16 | G22: =IF(MONTH((DATE($B$3,$D$3,1)-(WEEKDAY(DATE($B$3,$D$3,1))-1)+20))<>$D$3,"",DAY((DATE($B$3,$D$3,1)-(WEEKDAY(DATE($B$3,$D$3,1))-1)+20))) -> 17
A23: =IF(MONTH((DATE($B$3,$D$3,1)-(WEEKDAY(DATE($B$3,$D$3,1))-1)+14))<>$D$3,"",SUMIFS('Bill Tracker'!$C$3:$C$52,'Bill Tracker'!$R$3:$R$52,(DATE($B$3,$D$3,1)-(WEEKDAY(DATE($B$3,$D$3,1))-1)+14))) -> 0 | B23: =IF(MONTH((DATE($B$3,$D$3,1)-(WEEKDAY(DATE($B$3,$D$3,1))-1)+15))<>$D$3,"",SUMIFS('Bill Tracker'!$C$3:$C$52,'Bill Tracker'!$R$3:$R$52,(DATE($B$3,$D$3,1)-(WEEKDAY(DATE($B$3,$D$3,1))-1)+15))) -> 0 | C23: =IF(MONTH((DATE($B$3,$D$3,1)-(WEEKDAY(DATE($B$3,$D$3,1))-1)+16))<>$D$3,"",SUMIFS('Bill Tracker'!$C$3:$C$52,'Bill Tracker'!$R$3:$R$52,(DATE($B$3,$D$3,1)-(WEEKDAY(DATE($B$3,$D$3,1))-1)+16))) -> 0 | D23: =IF(MONTH((DATE($B$3,$D$3,1)-(WEEKDAY(DATE($B$3,$D$3,1))-1)+17))<>$D$3,"",SUMIFS('Bill Tracker'!$C$3:$C$52,'Bill Tracker'!$R$3:$R$52,(DATE($B$3,$D$3,1)-(WEEKDAY(DATE($B$3,$D$3,1))-1)+17))) -> 0 | E23: =IF(MONTH((DATE($B$3,$D$3,1)-(WEEKDAY(DATE($B$3,$D$3,1))-1)+18))<>$D$3,"",SUMIFS('Bill Tracker'!$C$3:$C$52,'Bill Tracker'!$R$3:$R$52,(DATE($B$3,$D$3,1)-(WEEKDAY(DATE($B$3,$D$3,1))-1)+18))) -> 0 | F23: =IF(MONTH((DATE($B$3,$D$3,1)-(WEEKDAY(DATE($B$3,$D$3,1))-1)+19))<>$D$3,"",SUMIFS('Bill Tracker'!$C$3:$C$52,'Bill Tracker'!$R$3:$R$52,(DATE($B$3,$D$3,1)-(WEEKDAY(DATE($B$3,$D$3,1))-1)+19))) -> 0 | G23: =IF(MONTH((DATE($B$3,$D$3,1)-(WEEKDAY(DATE($B$3,$D$3,1))-1)+20))<>$D$3,"",SUMIFS('Bill Tracker'!$C$3:$C$52,'Bill Tracker'!$R$3:$R$52,(DATE($B$3,$D$3,1)-(WEEKDAY(DATE($B$3,$D$3,1))-1)+20))) -> 0
A24: =IF(MONTH((DATE($B$3,$D$3,1)-(WEEKDAY(DATE($B$3,$D$3,1))-1)+21))<>$D$3,"",DAY((DATE($B$3,$D$3,1)-(WEEKDAY(DATE($B$3,$D$3,1))-1)+21))) -> 18 | B24: =IF(MONTH((DATE($B$3,$D$3,1)-(WEEKDAY(DATE($B$3,$D$3,1))-1)+22))<>$D$3,"",DAY((DATE($B$3,$D$3,1)-(WEEKDAY(DATE($B$3,$D$3,1))-1)+22))) -> 19 | C24: =IF(MONTH((DATE($B$3,$D$3,1)-(WEEKDAY(DATE($B$3,$D$3,1))-1)+23))<>$D$3,"",DAY((DATE($B$3,$D$3,1)-(WEEKDAY(DATE($B$3,$D$3,1))-1)+23))) -> 20 | D24: =IF(MONTH((DATE($B$3,$D$3,1)-(WEEKDAY(DATE($B$3,$D$3,1))-1)+24))<>$D$3,"",DAY((DATE($B$3,$D$3,1)-(WEEKDAY(DATE($B$3,$D$3,1))-1)+24))) -> 21 | E24: =IF(MONTH((DATE($B$3,$D$3,1)-(WEEKDAY(DATE($B$3,$D$3,1))-1)+25))<>$D$3,"",DAY((DATE($B$3,$D$3,1)-(WEEKDAY(DATE($B$3,$D$3,1))-1)+25))) -> 22 | F24: =IF(MONTH((DATE($B$3,$D$3,1)-(WEEKDAY(DATE($B$3,$D$3,1))-1)+26))<>$D$3,"",DAY((DATE($B$3,$D$3,1)-(WEEKDAY(DATE($B$3,$D$3,1))-1)+26))) -> 23 | G24: =IF(MONTH((DATE($B$3,$D$3,1)-(WEEKDAY(DATE($B$3,$D$3,1))-1)+27))<>$D$3,"",DAY((DATE($B$3,$D$3,1)-(WEEKDAY(DATE($B$3,$D$3,1))-1)+27))) -> 24
A25: =IF(MONTH((DATE($B$3,$D$3,1)-(WEEKDAY(DATE($B$3,$D$3,1))-1)+21))<>$D$3,"",SUMIFS('Bill Tracker'!$C$3:$C$52,'Bill Tracker'!$R$3:$R$52,(DATE($B$3,$D$3,1)-(WEEKDAY(DATE($B$3,$D$3,1))-1)+21))) -> 0 | B25: =IF(MONTH((DATE($B$3,$D$3,1)-(WEEKDAY(DATE($B$3,$D$3,1))-1)+22))<>$D$3,"",SUMIFS('Bill Tracker'!$C$3:$C$52,'Bill Tracker'!$R$3:$R$52,(DATE($B$3,$D$3,1)-(WEEKDAY(DATE($B$3,$D$3,1))-1)+22))) -> 0 | C25: =IF(MONTH((DATE($B$3,$D$3,1)-(WEEKDAY(DATE($B$3,$D$3,1))-1)+23))<>$D$3,"",SUMIFS('Bill Tracker'!$C$3:$C$52,'Bill Tracker'!$R$3:$R$52,(DATE($B$3,$D$3,1)-(WEEKDAY(DATE($B$3,$D$3,1))-1)+23))) -> 0 | D25: =IF(MONTH((DATE($B$3,$D$3,1)-(WEEKDAY(DATE($B$3,$D$3,1))-1)+24))<>$D$3,"",SUMIFS('Bill Tracker'!$C$3:$C$52,'Bill Tracker'!$R$3:$R$52,(DATE($B$3,$D$3,1)-(WEEKDAY(DATE($B$3,$D$3,1))-1)+24))) -> 0 | E25: =IF(MONTH((DATE($B$3,$D$3,1)-(WEEKDAY(DATE($B$3,$D$3,1))-1)+25))<>$D$3,"",SUMIFS('Bill Tracker'!$C$3:$C$52,'Bill Tracker'!$R$3:$R$52,(DATE($B$3,$D$3,1)-(WEEKDAY(DATE($B$3,$D$3,1))-1)+25))) -> 0 | F25: =IF(MONTH((DATE($B$3,$D$3,1)-(WEEKDAY(DATE($B$3,$D$3,1))-1)+26))<>$D$3,"",SUMIFS('Bill Tracker'!$C$3:$C$52,'Bill Tracker'!$R$3:$R$52,(DATE($B$3,$D$3,1)-(WEEKDAY(DATE($B$3,$D$3,1))-1)+26))) -> 0 | G25: =IF(MONTH((DATE($B$3,$D$3,1)-(WEEKDAY(DATE($B$3,$D$3,1))-1)+27))<>$D$3,"",SUMIFS('Bill Tracker'!$C$3:$C$52,'Bill Tracker'!$R$3:$R$52,(DATE($B$3,$D$3,1)-(WEEKDAY(DATE($B$3,$D$3,1))-1)+27))) -> 0
A26: =IF(MONTH((DATE($B$3,$D$3,1)-(WEEKDAY(DATE($B$3,$D$3,1))-1)+28))<>$D$3,"",DAY((DATE($B$3,$D$3,1)-(WEEKDAY(DATE($B$3,$D$3,1))-1)+28))) -> 25 | B26: =IF(MONTH((DATE($B$3,$D$3,1)-(WEEKDAY(DATE($B$3,$D$3,1))-1)+29))<>$D$3,"",DAY((DATE($B$3,$D$3,1)-(WEEKDAY(DATE($B$3,$D$3,1))-1)+29))) -> 26 | C26: =IF(MONTH((DATE($B$3,$D$3,1)-(WEEKDAY(DATE($B$3,$D$3,1))-1)+30))<>$D$3,"",DAY((DATE($B$3,$D$3,1)-(WEEKDAY(DATE($B$3,$D$3,1))-1)+30))) -> 27 | D26: =IF(MONTH((DATE($B$3,$D$3,1)-(WEEKDAY(DATE($B$3,$D$3,1))-1)+31))<>$D$3,"",DAY((DATE($B$3,$D$3,1)-(WEEKDAY(DATE($B$3,$D$3,1))-1)+31))) -> 28 | E26: =IF(MONTH((DATE($B$3,$D$3,1)-(WEEKDAY(DATE($B$3,$D$3,1))-1)+32))<>$D$3,"",DAY((DATE($B$3,$D$3,1)-(WEEKDAY(DATE($B$3,$D$3,1))-1)+32))) -> 29 | F26: =IF(MONTH((DATE($B$3,$D$3,1)-(WEEKDAY(DATE($B$3,$D$3,1))-1)+33))<>$D$3,"",DAY((DATE($B$3,$D$3,1)-(WEEKDAY(DATE($B$3,$D$3,1))-1)+33))) -> 30 | G26: =IF(MONTH((DATE($B$3,$D$3,1)-(WEEKDAY(DATE($B$3,$D$3,1))-1)+34))<>$D$3,"",DAY((DATE($B$3,$D$3,1)-(WEEKDAY(DATE($B$3,$D$3,1))-1)+34))) -> 31
A27: =IF(MONTH((DATE($B$3,$D$3,1)-(WEEKDAY(DATE($B$3,$D$3,1))-1)+28))<>$D$3,"",SUMIFS('Bill Tracker'!$C$3:$C$52,'Bill Tracker'!$R$3:$R$52,(DATE($B$3,$D$3,1)-(WEEKDAY(DATE($B$3,$D$3,1))-1)+28))) -> 0 | B27: =IF(MONTH((DATE($B$3,$D$3,1)-(WEEKDAY(DATE($B$3,$D$3,1))-1)+29))<>$D$3,"",SUMIFS('Bill Tracker'!$C$3:$C$52,'Bill Tracker'!$R$3:$R$52,(DATE($B$3,$D$3,1)-(WEEKDAY(DATE($B$3,$D$3,1))-1)+29))) -> 0 | C27: =IF(MONTH((DATE($B$3,$D$3,1)-(WEEKDAY(DATE($B$3,$D$3,1))-1)+30))<>$D$3,"",SUMIFS('Bill Tracker'!$C$3:$C$52,'Bill Tracker'!$R$3:$R$52,(DATE($B$3,$D$3,1)-(WEEKDAY(DATE($B$3,$D$3,1))-1)+30))) -> 0 | D27: =IF(MONTH((DATE($B$3,$D$3,1)-(WEEKDAY(DATE($B$3,$D$3,1))-1)+31))<>$D$3,"",SUMIFS('Bill Tracker'!$C$3:$C$52,'Bill Tracker'!$R$3:$R$52,(DATE($B$3,$D$3,1)-(WEEKDAY(DATE($B$3,$D$3,1))-1)+31))) -> 0 | E27: =IF(MONTH((DATE($B$3,$D$3,1)-(WEEKDAY(DATE($B$3,$D$3,1))-1)+32))<>$D$3,"",SUMIFS('Bill Tracker'!$C$3:$C$52,'Bill Tracker'!$R$3:$R$52,(DATE($B$3,$D$3,1)-(WEEKDAY(DATE($B$3,$D$3,1))-1)+32))) -> 0 | F27: =IF(MONTH((DATE($B$3,$D$3,1)-(WEEKDAY(DATE($B$3,$D$3,1))-1)+33))<>$D$3,"",SUMIFS('Bill Tracker'!$C$3:$C$52,'Bill Tracker'!$R$3:$R$52,(DATE($B$3,$D$3,1)-(WEEKDAY(DATE($B$3,$D$3,1))-1)+33))) -> 0 | G27: =IF(MONTH((DATE($B$3,$D$3,1)-(WEEKDAY(DATE($B$3,$D$3,1))-1)+34))<>$D$3,"",SUMIFS('Bill Tracker'!$C$3:$C$52,'Bill Tracker'!$R$3:$R$52,(DATE($B$3,$D$3,1)-(WEEKDAY(DATE($B$3,$D$3,1))-1)+34))) -> 0
A28: =IF(MONTH((DATE($B$3,$D$3,1)-(WEEKDAY(DATE($B$3,$D$3,1))-1)+35))<>$D$3,"",DAY((DATE($B$3,$D$3,1)-(WEEKDAY(DATE($B$3,$D$3,1))-1)+35))) | B28: =IF(MONTH((DATE($B$3,$D$3,1)-(WEEKDAY(DATE($B$3,$D$3,1))-1)+36))<>$D$3,"",DAY((DATE($B$3,$D$3,1)-(WEEKDAY(DATE($B$3,$D$3,1))-1)+36))) | C28: =IF(MONTH((DATE($B$3,$D$3,1)-(WEEKDAY(DATE($B$3,$D$3,1))-1)+37))<>$D$3,"",DAY((DATE($B$3,$D$3,1)-(WEEKDAY(DATE($B$3,$D$3,1))-1)+37))) | D28: =IF(MONTH((DATE($B$3,$D$3,1)-(WEEKDAY(DATE($B$3,$D$3,1))-1)+38))<>$D$3,"",DAY((DATE($B$3,$D$3,1)-(WEEKDAY(DATE($B$3,$D$3,1))-1)+38))) | E28: =IF(MONTH((DATE($B$3,$D$3,1)-(WEEKDAY(DATE($B$3,$D$3,1))-1)+39))<>$D$3,"",DAY((DATE($B$3,$D$3,1)-(WEEKDAY(DATE($B$3,$D$3,1))-1)+39))) | F28: =IF(MONTH((DATE($B$3,$D$3,1)-(WEEKDAY(DATE($B$3,$D$3,1))-1)+40))<>$D$3,"",DAY((DATE($B$3,$D$3,1)-(WEEKDAY(DATE($B$3,$D$3,1))-1)+40))) | G28: =IF(MONTH((DATE($B$3,$D$3,1)-(WEEKDAY(DATE($B$3,$D$3,1))-1)+41))<>$D$3,"",DAY((DATE($B$3,$D$3,1)-(WEEKDAY(DATE($B$3,$D$3,1))-1)+41)))
A29: =IF(MONTH((DATE($B$3,$D$3,1)-(WEEKDAY(DATE($B$3,$D$3,1))-1)+35))<>$D$3,"",SUMIFS('Bill Tracker'!$C$3:$C$52,'Bill Tracker'!$R$3:$R$52,(DATE($B$3,$D$3,1)-(WEEKDAY(DATE($B$3,$D$3,1))-1)+35))) | B29: =IF(MONTH((DATE($B$3,$D$3,1)-(WEEKDAY(DATE($B$3,$D$3,1))-1)+36))<>$D$3,"",SUMIFS('Bill Tracker'!$C$3:$C$52,'Bill Tracker'!$R$3:$R$52,(DATE($B$3,$D$3,1)-(WEEKDAY(DATE($B$3,$D$3,1))-1)+36))) | C29: =IF(MONTH((DATE($B$3,$D$3,1)-(WEEKDAY(DATE($B$3,$D$3,1))-1)+37))<>$D$3,"",SUMIFS('Bill Tracker'!$C$3:$C$52,'Bill Tracker'!$R$3:$R$52,(DATE($B$3,$D$3,1)-(WEEKDAY(DATE($B$3,$D$3,1))-1)+37))) | D29: =IF(MONTH((DATE($B$3,$D$3,1)-(WEEKDAY(DATE($B$3,$D$3,1))-1)+38))<>$D$3,"",SUMIFS('Bill Tracker'!$C$3:$C$52,'Bill Tracker'!$R$3:$R$52,(DATE($B$3,$D$3,1)-(WEEKDAY(DATE($B$3,$D$3,1))-1)+38))) | E29: =IF(MONTH((DATE($B$3,$D$3,1)-(WEEKDAY(DATE($B$3,$D$3,1))-1)+39))<>$D$3,"",SUMIFS('Bill Tracker'!$C$3:$C$52,'Bill Tracker'!$R$3:$R$52,(DATE($B$3,$D$3,1)-(WEEKDAY(DATE($B$3,$D$3,1))-1)+39))) | F29: =IF(MONTH((DATE($B$3,$D$3,1)-(WEEKDAY(DATE($B$3,$D$3,1))-1)+40))<>$D$3,"",SUMIFS('Bill Tracker'!$C$3:$C$52,'Bill Tracker'!$R$3:$R$52,(DATE($B$3,$D$3,1)-(WEEKDAY(DATE($B$3,$D$3,1))-1)+40))) | G29: =IF(MONTH((DATE($B$3,$D$3,1)-(WEEKDAY(DATE($B$3,$D$3,1))-1)+41))<>$D$3,"",SUMIFS('Bill Tracker'!$C$3:$C$52,'Bill Tracker'!$R$3:$R$52,(DATE($B$3,$D$3,1)-(WEEKDAY(DATE($B$3,$D$3,1))-1)+41)))
