Workbook

Sheet Instructions
A1: How to Use This Dashboard
A3: 1. Log every sale in the 'Sales Tracker' tab — Date, Order #, Item, Qty, and Price. Total is calculated automatically.
A4: 2. Log every business cost in the 'Expense Tracker' tab — Date, Category, Description, and Amount.
A5: 3. The 'Dashboard' tab summarizes your Total Sales, Total Expenses, Net Profit, and Average Order Value automatically.
A6: 4. The 'Profit Calculator' tab shows your Net Profit and Profit Margin based on the totals from both trackers.
A7: 5. Only edit the white/unshaded cells. Shaded header cells and formula cells (Total rows, Dashboard tiles) update automatically — do not overwrite them.
A8: 6. Add more rows to a tracker by selecting a formatted row and copying it down; formulas will carry over.
A10: Prepared for {{CLIENT_NAME}} ({{NICHE}}). Amounts are in {{CURRENCY}}.

Sheet Dashboard
A1: {{CLIENT_NAME}}
A2: {{NICHE}} — Etsy Seller Dashboard
A3: All figures shown in {{CURRENCY}} unless otherwise noted.
A5: Total Sales ({{CURRENCY}}) | B5: Total Expenses ({{CURRENCY}}) | C5: Net Profit ({{CURRENCY}}) | D5: Avg Order Value ({{CURRENCY}})
A6: ='Sales Tracker'!F19 -> 0 | B6: ='Expense Tracker'!D19 -> 0 | C6: =A6-B6 -> 0 | D6: =IFERROR(A6/COUNTIF('Sales Tracker'!F3:F17,">0"),0) -> 0
A8: Quick Links: see 'Sales Tracker', 'Expense Tracker', and 'Profit Calculator' tabs to log activity.

Sheet Sales Tracker
A1: {{CLIENT_NAME}} — Sales Tracker
A2: Date | B2: Order # | C2: Item | D2: Qty | E2: Price ({{CURRENCY}}) | F2: Total ({{CURRENCY}})
F3: =IFERROR(D3*E3,0) -> 0
F4: =IFERROR(D4*E4,0) -> 0
F5: =IFERROR(D5*E5,0) -> 0
F6: =IFERROR(D6*E6,0) -> 0
F7: =IFERROR(D7*E7,0) -> 0
F8: =IFERROR(D8*E8,0) -> 0
F9: =IFERROR(D9*E9,0) -> 0
F10: =IFERROR(D10*E10,0) -> 0
F11: =IFERROR(D11*E11,0) -> 0
F12: =IFERROR(D12*E12,0) -> 0
F13: =IFERROR(D13*E13,0) -> 0
F14: =IFERROR(D14*E14,0) -> 0
... F17: =IFERROR(D17*E17,0) -> 0
E19: Total: | F19: =SUM(F3:F17) -> 0

Sheet Expense Tracker
A1: {{CLIENT_NAME}} — Expense Tracker
A2: Date | B2: Category | C2: Description | D2: Amount ({{CURRENCY}})
C19: Total: | D19: =SUM(D3:D17) -> 0

Sheet Profit Calculator
A1: {{CLIENT_NAME}} — Profit Calculator
A2: {{NICHE}} — figures in {{CURRENCY}}
A4: Total Sales ({{CURRENCY}}) | B4: ='Sales Tracker'!F19 -> 0
A5: Total Expenses ({{CURRENCY}}) | B5: ='Expense Tracker'!D19 -> 0
A6: Net Profit ({{CURRENCY}}) | B6: =B4-B5 -> 0
A7: Profit Margin (%) | B7: =IFERROR(B6/B4,0) -> 0
