Workbook

Sheet Instructions
A1: How to Use This Pricing Calculator
A4: 1. Open 'Setup' first. Set your hourly labor rate, overhead %, desired markup %, and your marketplace's fee structure (defaults are Etsy's published rates — adjust if you sell elsewhere).
A5: 2. In 'Pricing Calculator', add a row per product: Materials Cost and Labor Hours. Everything else calculates automatically.
A6: 3. Five pricing methods are shown side by side: Cost-Plus Markup, Keystone (2x), Hourly Rate, Value-Based (you set it), and Competitor-Matched (you set it) — so you can compare before deciding.
A7: 4. 'Recommended Price' averages the three calculated methods. 'Your Listed Price' defaults to that but you can type over it with whatever you actually plan to charge.
A8: 5. 'Net Profit After Fees' and 'Net Margin After Fees' show what you actually keep once marketplace fees come out — not just your markup on paper.
A9: 6. Use the 'Break-Even Estimator' at the top of the Pricing Calculator tab to see how many units of a chosen product you need to sell per month to cover your fixed overhead.
A10: 7. Only edit yellow (input) or white cells. Green-header and formula cells update automatically — do not overwrite them.
A12: Prepared for {{CLIENT_NAME}} ({{NICHE}}). Amounts are in {{CURRENCY}}.

Sheet Setup
A1: {{CLIENT_NAME}} — Setup
A2: {{NICHE}} — configure once, everything else updates automatically
A3: Setting | B3: Value
A4: Hourly Labor Rate ({{CURRENCY}}) | B4: 20
A5: Overhead % (of materials + labor) | B5: 0.15
A6: Desired Markup % (Cost-Plus method) | B6: 0.5
A7: Marketplace Transaction Fee % | B7: 0.065
A8: Marketplace Payment Processing % | B8: 0.03
A9: Marketplace Payment Processing Fixed Fee ({{CURRENCY}}) | B9: 0.25
A10: Marketplace Listing Fee per Sale ({{CURRENCY}}) | B10: 0.2
A11: Monthly Fixed Overhead ({{CURRENCY}}) | B11: 300
A13: Defaults reflect Etsy's published US fee structure as a starting point — update these if you sell elsewhere or rates change. Listing fee is amortized as a flat per-sale cost for simplicity.

Sheet Pricing Calculator
A1: {{CLIENT_NAME}} — Pricing Calculator
A2: {{NICHE}} — 5 pricing methods, figures in {{CURRENCY}}
A3: Break-Even Estimator | S3: Pricing Method Comparison — Selected Product
A4: Product | C4: Profit per Unit ({{CURRENCY}}) | D4: Units/Month to Break Even | S4: Method | T4: Price
C5: =IFERROR(INDEX($P$9:$P$58,MATCH(B4,$A$9:$A$58,0)),"") | D5: =IF(C5="","",IF(C5<=0,"N/A — no profit at this price",ROUNDUP(Setup!$B$11/C5,0))) | S5: Cost-Plus | T5: =IFERROR(INDEX(H9:H58,MATCH($B$4,$A$9:$A$58,0)),0) -> 0
S6: Keystone (2x) | T6: =IFERROR(INDEX(I9:I58,MATCH($B$4,$A$9:$A$58,0)),0) -> 0
A7: Product Pricing Table — enter Materials Cost and Labor Hours; everything else calculates automatically. | S7: Hourly Rate | T7: =IFERROR(INDEX(J9:J58,MATCH($B$4,$A$9:$A$58,0)),0) -> 0
A8: Product | B8: Materials ({{CURRENCY}}) | C8: Labor Hours | D8: Hourly Rate ({{CURRENCY}}) | E8: Labor Cost ({{CURRENCY}}) | F8: Overhead ({{CURRENCY}}) | G8: Total Cost ({{CURRENCY}}) | H8: Cost-Plus Price | I8: Keystone (2x) Price | J8: Hourly Rate Price | K8: Value-Based Price | L8: Competitor Price | M8: Recommended Price | N8: Your Listed Price | O8: Marketplace Fees | P8: Net Profit | Q8: Net Margin | S8: Value-Based | T8: =IFERROR(INDEX(K9:K58,MATCH($B$4,$A$9:$A$58,0)),0) -> 0
D9: =IF(A9="","",Setup!$B$4) | E9: =IF(A9="","",C9*D9) | F9: =IF(A9="","",(B9+E9)*Setup!$B$5) | G9: =IF(A9="","",B9+E9+F9) | H9: =IF(A9="","",G9*(1+Setup!$B$6)) | I9: =IF(A9="","",G9*2) | J9: =IF(A9="","",E9+B9) | M9: =IF(A9="","",AVERAGE(H9:J9)) | N9: =IF(A9="","",M9) | O9: =IF(A9="","",Setup!$B$10+N9*Setup!$B$7+N9*Setup!$B$8+Setup!$B$9) | P9: =IF(A9="","",N9-G9-O9) | Q9: =IF(A9="","",IFERROR(P9/N9,0)) | S9: Competitor | T9: =IFERROR(INDEX(L9:L58,MATCH($B$4,$A$9:$A$58,0)),0) -> 0
D10: =IF(A10="","",Setup!$B$4) | E10: =IF(A10="","",C10*D10) | F10: =IF(A10="","",(B10+E10)*Setup!$B$5) | G10: =IF(A10="","",B10+E10+F10) | H10: =IF(A10="","",G10*(1+Setup!$B$6)) | I10: =IF(A10="","",G10*2) | J10: =IF(A10="","",E10+B10) | M10: =IF(A10="","",AVERAGE(H10:J10)) | N10: =IF(A10="","",M10) | O10: =IF(A10="","",Setup!$B$10+N10*Setup!$B$7+N10*Setup!$B$8+Setup!$B$9) | P10: =IF(A10="","",N10-G10-O10) | Q10: =IF(A10="","",IFERROR(P10/N10,0))
D11: =IF(A11="","",Setup!$B$4) | E11: =IF(A11="","",C11*D11) | F11: =IF(A11="","",(B11+E11)*Setup!$B$5) | G11: =IF(A11="","",B11+E11+F11) | H11: =IF(A11="","",G11*(1+Setup!$B$6)) | I11: =IF(A11="","",G11*2) | J11: =IF(A11="","",E11+B11) | M11: =IF(A11="","",AVERAGE(H11:J11)) | N11: =IF(A11="","",M11) | O11: =IF(A11="","",Setup!$B$10+N11*Setup!$B$7+N11*Setup!$B$8+Setup!$B$9) | P11: =IF(A11="","",N11-G11-O11) | Q11: =IF(A11="","",IFERROR(P11/N11,0))
D12: =IF(A12="","",Setup!$B$4) | E12: =IF(A12="","",C12*D12) | F12: =IF(A12="","",(B12+E12)*Setup!$B$5) | G12: =IF(A12="","",B12+E12+F12) | H12: =IF(A12="","",G12*(1+Setup!$B$6)) | I12: =IF(A12="","",G12*2) | J12: =IF(A12="","",E12+B12) | M12: =IF(A12="","",AVERAGE(H12:J12)) | N12: =IF(A12="","",M12) | O12: =IF(A12="","",Setup!$B$10+N12*Setup!$B$7+N12*Setup!$B$8+Setup!$B$9) | P12: =IF(A12="","",N12-G12-O12) | Q12: =IF(A12="","",IFERROR(P12/N12,0))
D13: =IF(A13="","",Setup!$B$4) | E13: =IF(A13="","",C13*D13) | F13: =IF(A13="","",(B13+E13)*Setup!$B$5) | G13: =IF(A13="","",B13+E13+F13) | H13: =IF(A13="","",G13*(1+Setup!$B$6)) | I13: =IF(A13="","",G13*2) | J13: =IF(A13="","",E13+B13) | M13: =IF(A13="","",AVERAGE(H13:J13)) | N13: =IF(A13="","",M13) | O13: =IF(A13="","",Setup!$B$10+N13*Setup!$B$7+N13*Setup!$B$8+Setup!$B$9) | P13: =IF(A13="","",N13-G13-O13) | Q13: =IF(A13="","",IFERROR(P13/N13,0))
D14: =IF(A14="","",Setup!$B$4) | E14: =IF(A14="","",C14*D14) | F14: =IF(A14="","",(B14+E14)*Setup!$B$5) | G14: =IF(A14="","",B14+E14+F14) | H14: =IF(A14="","",G14*(1+Setup!$B$6)) | I14: =IF(A14="","",G14*2) | J14: =IF(A14="","",E14+B14) | M14: =IF(A14="","",AVERAGE(H14:J14)) | N14: =IF(A14="","",M14) | O14: =IF(A14="","",Setup!$B$10+N14*Setup!$B$7+N14*Setup!$B$8+Setup!$B$9) | P14: =IF(A14="","",N14-G14-O14) | Q14: =IF(A14="","",IFERROR(P14/N14,0))
D15: =IF(A15="","",Setup!$B$4) | E15: =IF(A15="","",C15*D15) | F15: =IF(A15="","",(B15+E15)*Setup!$B$5) | G15: =IF(A15="","",B15+E15+F15) | H15: =IF(A15="","",G15*(1+Setup!$B$6)) | I15: =IF(A15="","",G15*2) | J15: =IF(A15="","",E15+B15) | M15: =IF(A15="","",AVERAGE(H15:J15)) | N15: =IF(A15="","",M15) | O15: =IF(A15="","",Setup!$B$10+N15*Setup!$B$7+N15*Setup!$B$8+Setup!$B$9) | P15: =IF(A15="","",N15-G15-O15) | Q15: =IF(A15="","",IFERROR(P15/N15,0))
D16: =IF(A16="","",Setup!$B$4) | E16: =IF(A16="","",C16*D16) | F16: =IF(A16="","",(B16+E16)*Setup!$B$5) | G16: =IF(A16="","",B16+E16+F16) | H16: =IF(A16="","",G16*(1+Setup!$B$6)) | I16: =IF(A16="","",G16*2) | J16: =IF(A16="","",E16+B16) | M16: =IF(A16="","",AVERAGE(H16:J16)) | N16: =IF(A16="","",M16) | O16: =IF(A16="","",Setup!$B$10+N16*Setup!$B$7+N16*Setup!$B$8+Setup!$B$9) | P16: =IF(A16="","",N16-G16-O16) | Q16: =IF(A16="","",IFERROR(P16/N16,0))
D17: =IF(A17="","",Setup!$B$4) | E17: =IF(A17="","",C17*D17) | F17: =IF(A17="","",(B17+E17)*Setup!$B$5) | G17: =IF(A17="","",B17+E17+F17) | H17: =IF(A17="","",G17*(1+Setup!$B$6)) | I17: =IF(A17="","",G17*2) | J17: =IF(A17="","",E17+B17) | M17: =IF(A17="","",AVERAGE(H17:J17)) | N17: =IF(A17="","",M17) | O17: =IF(A17="","",Setup!$B$10+N17*Setup!$B$7+N17*Setup!$B$8+Setup!$B$9) | P17: =IF(A17="","",N17-G17-O17) | Q17: =IF(A17="","",IFERROR(P17/N17,0))
D18: =IF(A18="","",Setup!$B$4) | E18: =IF(A18="","",C18*D18) | F18: =IF(A18="","",(B18+E18)*Setup!$B$5) | G18: =IF(A18="","",B18+E18+F18) | H18: =IF(A18="","",G18*(1+Setup!$B$6)) | I18: =IF(A18="","",G18*2) | J18: =IF(A18="","",E18+B18) | M18: =IF(A18="","",AVERAGE(H18:J18)) | N18: =IF(A18="","",M18) | O18: =IF(A18="","",Setup!$B$10+N18*Setup!$B$7+N18*Setup!$B$8+Setup!$B$9) | P18: =IF(A18="","",N18-G18-O18) | Q18: =IF(A18="","",IFERROR(P18/N18,0))
D19: =IF(A19="","",Setup!$B$4) | E19: =IF(A19="","",C19*D19) | F19: =IF(A19="","",(B19+E19)*Setup!$B$5) | G19: =IF(A19="","",B19+E19+F19) | H19: =IF(A19="","",G19*(1+Setup!$B$6)) | I19: =IF(A19="","",G19*2) | J19: =IF(A19="","",E19+B19) | M19: =IF(A19="","",AVERAGE(H19:J19)) | N19: =IF(A19="","",M19) | O19: =IF(A19="","",Setup!$B$10+N19*Setup!$B$7+N19*Setup!$B$8+Setup!$B$9) | P19: =IF(A19="","",N19-G19-O19) | Q19: =IF(A19="","",IFERROR(P19/N19,0))
D20: =IF(A20="","",Setup!$B$4) | E20: =IF(A20="","",C20*D20) | F20: =IF(A20="","",(B20+E20)*Setup!$B$5) | G20: =IF(A20="","",B20+E20+F20) | H20: =IF(A20="","",G20*(1+Setup!$B$6)) | I20: =IF(A20="","",G20*2) | J20: =IF(A20="","",E20+B20) | M20: =IF(A20="","",AVERAGE(H20:J20)) | N20: =IF(A20="","",M20) | O20: =IF(A20="","",Setup!$B$10+N20*Setup!$B$7+N20*Setup!$B$8+Setup!$B$9) | P20: =IF(A20="","",N20-G20-O20) | Q20: =IF(A20="","",IFERROR(P20/N20,0))
D21: =IF(A21="","",Setup!$B$4) | E21: =IF(A21="","",C21*D21) | F21: =IF(A21="","",(B21+E21)*Setup!$B$5) | G21: =IF(A21="","",B21+E21+F21) | H21: =IF(A21="","",G21*(1+Setup!$B$6)) | I21: =IF(A21="","",G21*2) | J21: =IF(A21="","",E21+B21) | M21: =IF(A21="","",AVERAGE(H21:J21)) | N21: =IF(A21="","",M21) | O21: =IF(A21="","",Setup!$B$10+N21*Setup!$B$7+N21*Setup!$B$8+Setup!$B$9) | P21: =IF(A21="","",N21-G21-O21) | Q21: =IF(A21="","",IFERROR(P21/N21,0))
... D58: =IF(A58="","",Setup!$B$4) | E58: =IF(A58="","",C58*D58) | F58: =IF(A58="","",(B58+E58)*Setup!$B$5) | G58: =IF(A58="","",B58+E58+F58) | H58: =IF(A58="","",G58*(1+Setup!$B$6)) | I58: =IF(A58="","",G58*2) | J58: =IF(A58="","",E58+B58) | M58: =IF(A58="","",AVERAGE(H58:J58)) | N58: =IF(A58="","",M58) | O58: =IF(A58="","",Setup!$B$10+N58*Setup!$B$7+N58*Setup!$B$8+Setup!$B$9) | P58: =IF(A58="","",N58-G58-O58) | Q58: =IF(A58="","",IFERROR(P58/N58,0))
