Workbook

Sheet Instructions
A1: How to Use This Small Business Tracker
A4: 1. Open 'Setup' first. Set your business info, tax rate, and product categories.
A5: 2. Add every product you sell in 'Inventory Tracker' — cost, price, quantity on hand, and reorder level. Low-stock items are flagged automatically.
A6: 3. Add every customer in 'Customer Tracker' — their order count and total spend update automatically once you log orders.
A7: 4. Log every sale in 'Order Tracker'. Give every line of the same order the same Invoice # — Unit Price is pulled from Inventory automatically.
A8: 5. Enter an Invoice # in 'Invoice Generator' to produce a ready-to-send invoice for that order, pulling every matching line item automatically.
A9: 6. 'Sales Dashboard' and 'Customer Insights' update automatically from your order history — no manual entry needed.
A10: 7. Only edit yellow (input) or white cells. Green-header and formula cells update automatically — do not overwrite them.
A11: 8. To log more than the pre-formatted rows, select the last formatted row in a tracker and copy it downward; formulas will carry over.
A13: Prepared for {{CLIENT_NAME}} ({{NICHE}}). Amounts are in {{CURRENCY}}.

Sheet Setup
A1: {{CLIENT_NAME}} — Setup
A2: {{NICHE}} — configure once, everything else updates automatically
A3: Setting | B3: Value
A4: Business Email | B4: hello@example.com
A5: Tax Rate (%) | B5: 0.1
A6: Invoice Prefix | B6: INV-
A8: Product Categories | C8: Order Status Options | D8: Payment Status Options
A9: Apparel | C9: Pending | D9: Unpaid
A10: Accessories | C10: In Production | D10: Paid
A11: Home Goods | C11: Shipped | D11: Refunded
A12: Digital | C12: Delivered
A13: Custom / Made-to-Order | C13: Cancelled
A14: Other

Sheet Customer Tracker
A1: {{CLIENT_NAME}} — Customer Tracker
A2: Customer ID | B2: Name | C2: Email | D2: Phone | E2: Address | F2: Total Orders | G2: Total Spent ({{CURRENCY}}) | H2: Last Order Date | I2: Customer Since | J2: Notes | K2: Spend Rank
A3: =IF(B3="","",ROW()-3+1) | F3: =IF(B3="","",COUNTIFS('Order Tracker'!$E$3:$E$102,B3,'Order Tracker'!$B$3:$B$102,1)) | G3: =IF(B3="","",SUMIFS('Order Tracker'!$I$3:$I$102,'Order Tracker'!$E$3:$E$102,B3)) | H3: =IF(B3="","",IFERROR(_xlfn.MAXIFS('Order Tracker'!$D$3:$D$102,'Order Tracker'!$E$3:$E$102,B3),"")) | K3: =IF(B3="","",RANK(G3,$G$3:$G$52)+COUNTIF($G$3:G3,G3)-1)
A4: =IF(B4="","",ROW()-3+1) | F4: =IF(B4="","",COUNTIFS('Order Tracker'!$E$3:$E$102,B4,'Order Tracker'!$B$3:$B$102,1)) | G4: =IF(B4="","",SUMIFS('Order Tracker'!$I$3:$I$102,'Order Tracker'!$E$3:$E$102,B4)) | H4: =IF(B4="","",IFERROR(_xlfn.MAXIFS('Order Tracker'!$D$3:$D$102,'Order Tracker'!$E$3:$E$102,B4),"")) | K4: =IF(B4="","",RANK(G4,$G$3:$G$52)+COUNTIF($G$3:G4,G4)-1)
A5: =IF(B5="","",ROW()-3+1) | F5: =IF(B5="","",COUNTIFS('Order Tracker'!$E$3:$E$102,B5,'Order Tracker'!$B$3:$B$102,1)) | G5: =IF(B5="","",SUMIFS('Order Tracker'!$I$3:$I$102,'Order Tracker'!$E$3:$E$102,B5)) | H5: =IF(B5="","",IFERROR(_xlfn.MAXIFS('Order Tracker'!$D$3:$D$102,'Order Tracker'!$E$3:$E$102,B5),"")) | K5: =IF(B5="","",RANK(G5,$G$3:$G$52)+COUNTIF($G$3:G5,G5)-1)
A6: =IF(B6="","",ROW()-3+1) | F6: =IF(B6="","",COUNTIFS('Order Tracker'!$E$3:$E$102,B6,'Order Tracker'!$B$3:$B$102,1)) | G6: =IF(B6="","",SUMIFS('Order Tracker'!$I$3:$I$102,'Order Tracker'!$E$3:$E$102,B6)) | H6: =IF(B6="","",IFERROR(_xlfn.MAXIFS('Order Tracker'!$D$3:$D$102,'Order Tracker'!$E$3:$E$102,B6),"")) | K6: =IF(B6="","",RANK(G6,$G$3:$G$52)+COUNTIF($G$3:G6,G6)-1)
A7: =IF(B7="","",ROW()-3+1) | F7: =IF(B7="","",COUNTIFS('Order Tracker'!$E$3:$E$102,B7,'Order Tracker'!$B$3:$B$102,1)) | G7: =IF(B7="","",SUMIFS('Order Tracker'!$I$3:$I$102,'Order Tracker'!$E$3:$E$102,B7)) | H7: =IF(B7="","",IFERROR(_xlfn.MAXIFS('Order Tracker'!$D$3:$D$102,'Order Tracker'!$E$3:$E$102,B7),"")) | K7: =IF(B7="","",RANK(G7,$G$3:$G$52)+COUNTIF($G$3:G7,G7)-1)
A8: =IF(B8="","",ROW()-3+1) | F8: =IF(B8="","",COUNTIFS('Order Tracker'!$E$3:$E$102,B8,'Order Tracker'!$B$3:$B$102,1)) | G8: =IF(B8="","",SUMIFS('Order Tracker'!$I$3:$I$102,'Order Tracker'!$E$3:$E$102,B8)) | H8: =IF(B8="","",IFERROR(_xlfn.MAXIFS('Order Tracker'!$D$3:$D$102,'Order Tracker'!$E$3:$E$102,B8),"")) | K8: =IF(B8="","",RANK(G8,$G$3:$G$52)+COUNTIF($G$3:G8,G8)-1)
A9: =IF(B9="","",ROW()-3+1) | F9: =IF(B9="","",COUNTIFS('Order Tracker'!$E$3:$E$102,B9,'Order Tracker'!$B$3:$B$102,1)) | G9: =IF(B9="","",SUMIFS('Order Tracker'!$I$3:$I$102,'Order Tracker'!$E$3:$E$102,B9)) | H9: =IF(B9="","",IFERROR(_xlfn.MAXIFS('Order Tracker'!$D$3:$D$102,'Order Tracker'!$E$3:$E$102,B9),"")) | K9: =IF(B9="","",RANK(G9,$G$3:$G$52)+COUNTIF($G$3:G9,G9)-1)
A10: =IF(B10="","",ROW()-3+1) | F10: =IF(B10="","",COUNTIFS('Order Tracker'!$E$3:$E$102,B10,'Order Tracker'!$B$3:$B$102,1)) | G10: =IF(B10="","",SUMIFS('Order Tracker'!$I$3:$I$102,'Order Tracker'!$E$3:$E$102,B10)) | H10: =IF(B10="","",IFERROR(_xlfn.MAXIFS('Order Tracker'!$D$3:$D$102,'Order Tracker'!$E$3:$E$102,B10),"")) | K10: =IF(B10="","",RANK(G10,$G$3:$G$52)+COUNTIF($G$3:G10,G10)-1)
A11: =IF(B11="","",ROW()-3+1) | F11: =IF(B11="","",COUNTIFS('Order Tracker'!$E$3:$E$102,B11,'Order Tracker'!$B$3:$B$102,1)) | G11: =IF(B11="","",SUMIFS('Order Tracker'!$I$3:$I$102,'Order Tracker'!$E$3:$E$102,B11)) | H11: =IF(B11="","",IFERROR(_xlfn.MAXIFS('Order Tracker'!$D$3:$D$102,'Order Tracker'!$E$3:$E$102,B11),"")) | K11: =IF(B11="","",RANK(G11,$G$3:$G$52)+COUNTIF($G$3:G11,G11)-1)
A12: =IF(B12="","",ROW()-3+1) | F12: =IF(B12="","",COUNTIFS('Order Tracker'!$E$3:$E$102,B12,'Order Tracker'!$B$3:$B$102,1)) | G12: =IF(B12="","",SUMIFS('Order Tracker'!$I$3:$I$102,'Order Tracker'!$E$3:$E$102,B12)) | H12: =IF(B12="","",IFERROR(_xlfn.MAXIFS('Order Tracker'!$D$3:$D$102,'Order Tracker'!$E$3:$E$102,B12),"")) | K12: =IF(B12="","",RANK(G12,$G$3:$G$52)+COUNTIF($G$3:G12,G12)-1)
A13: =IF(B13="","",ROW()-3+1) | F13: =IF(B13="","",COUNTIFS('Order Tracker'!$E$3:$E$102,B13,'Order Tracker'!$B$3:$B$102,1)) | G13: =IF(B13="","",SUMIFS('Order Tracker'!$I$3:$I$102,'Order Tracker'!$E$3:$E$102,B13)) | H13: =IF(B13="","",IFERROR(_xlfn.MAXIFS('Order Tracker'!$D$3:$D$102,'Order Tracker'!$E$3:$E$102,B13),"")) | K13: =IF(B13="","",RANK(G13,$G$3:$G$52)+COUNTIF($G$3:G13,G13)-1)
A14: =IF(B14="","",ROW()-3+1) | F14: =IF(B14="","",COUNTIFS('Order Tracker'!$E$3:$E$102,B14,'Order Tracker'!$B$3:$B$102,1)) | G14: =IF(B14="","",SUMIFS('Order Tracker'!$I$3:$I$102,'Order Tracker'!$E$3:$E$102,B14)) | H14: =IF(B14="","",IFERROR(_xlfn.MAXIFS('Order Tracker'!$D$3:$D$102,'Order Tracker'!$E$3:$E$102,B14),"")) | K14: =IF(B14="","",RANK(G14,$G$3:$G$52)+COUNTIF($G$3:G14,G14)-1)
... A52: =IF(B52="","",ROW()-3+1) | F52: =IF(B52="","",COUNTIFS('Order Tracker'!$E$3:$E$102,B52,'Order Tracker'!$B$3:$B$102,1)) | G52: =IF(B52="","",SUMIFS('Order Tracker'!$I$3:$I$102,'Order Tracker'!$E$3:$E$102,B52)) | H52: =IF(B52="","",IFERROR(_xlfn.MAXIFS('Order Tracker'!$D$3:$D$102,'Order Tracker'!$E$3:$E$102,B52),"")) | K52: =IF(B52="","",RANK(G52,$G$3:$G$52)+COUNTIF($G$3:G52,G52)-1)

Sheet Inventory Tracker
A1: {{CLIENT_NAME}} — Inventory Tracker
A2: SKU | B2: Product Name | C2: Category | D2: Cost/Unit ({{CURRENCY}}) | E2: Price/Unit ({{CURRENCY}}) | F2: Qty on Hand | G2: Reorder Level | H2: Stock Value ({{CURRENCY}}) | I2: Potential Revenue ({{CURRENCY}}) | J2: Status | K2: Units Sold | L2: Revenue ({{CURRENCY}}) | M2: Sales Rank
H3: =IFERROR(D3*F3,0) -> 0 | I3: =IFERROR(E3*F3,0) -> 0 | J3: =IF(B3="","",IF(F3<=G3,"Reorder!","OK")) | K3: =IF(B3="","",SUMIFS('Order Tracker'!$G$3:$G$102,'Order Tracker'!$F$3:$F$102,B3)) | L3: =IF(B3="","",SUMIFS('Order Tracker'!$I$3:$I$102,'Order Tracker'!$F$3:$F$102,B3)) | M3: =IF(B3="","",RANK(L3,$L$3:$L$52)+COUNTIF($L$3:L3,L3)-1)
H4: =IFERROR(D4*F4,0) -> 0 | I4: =IFERROR(E4*F4,0) -> 0 | J4: =IF(B4="","",IF(F4<=G4,"Reorder!","OK")) | K4: =IF(B4="","",SUMIFS('Order Tracker'!$G$3:$G$102,'Order Tracker'!$F$3:$F$102,B4)) | L4: =IF(B4="","",SUMIFS('Order Tracker'!$I$3:$I$102,'Order Tracker'!$F$3:$F$102,B4)) | M4: =IF(B4="","",RANK(L4,$L$3:$L$52)+COUNTIF($L$3:L4,L4)-1)
H5: =IFERROR(D5*F5,0) -> 0 | I5: =IFERROR(E5*F5,0) -> 0 | J5: =IF(B5="","",IF(F5<=G5,"Reorder!","OK")) | K5: =IF(B5="","",SUMIFS('Order Tracker'!$G$3:$G$102,'Order Tracker'!$F$3:$F$102,B5)) | L5: =IF(B5="","",SUMIFS('Order Tracker'!$I$3:$I$102,'Order Tracker'!$F$3:$F$102,B5)) | M5: =IF(B5="","",RANK(L5,$L$3:$L$52)+COUNTIF($L$3:L5,L5)-1)
H6: =IFERROR(D6*F6,0) -> 0 | I6: =IFERROR(E6*F6,0) -> 0 | J6: =IF(B6="","",IF(F6<=G6,"Reorder!","OK")) | K6: =IF(B6="","",SUMIFS('Order Tracker'!$G$3:$G$102,'Order Tracker'!$F$3:$F$102,B6)) | L6: =IF(B6="","",SUMIFS('Order Tracker'!$I$3:$I$102,'Order Tracker'!$F$3:$F$102,B6)) | M6: =IF(B6="","",RANK(L6,$L$3:$L$52)+COUNTIF($L$3:L6,L6)-1)
H7: =IFERROR(D7*F7,0) -> 0 | I7: =IFERROR(E7*F7,0) -> 0 | J7: =IF(B7="","",IF(F7<=G7,"Reorder!","OK")) | K7: =IF(B7="","",SUMIFS('Order Tracker'!$G$3:$G$102,'Order Tracker'!$F$3:$F$102,B7)) | L7: =IF(B7="","",SUMIFS('Order Tracker'!$I$3:$I$102,'Order Tracker'!$F$3:$F$102,B7)) | M7: =IF(B7="","",RANK(L7,$L$3:$L$52)+COUNTIF($L$3:L7,L7)-1)
H8: =IFERROR(D8*F8,0) -> 0 | I8: =IFERROR(E8*F8,0) -> 0 | J8: =IF(B8="","",IF(F8<=G8,"Reorder!","OK")) | K8: =IF(B8="","",SUMIFS('Order Tracker'!$G$3:$G$102,'Order Tracker'!$F$3:$F$102,B8)) | L8: =IF(B8="","",SUMIFS('Order Tracker'!$I$3:$I$102,'Order Tracker'!$F$3:$F$102,B8)) | M8: =IF(B8="","",RANK(L8,$L$3:$L$52)+COUNTIF($L$3:L8,L8)-1)
H9: =IFERROR(D9*F9,0) -> 0 | I9: =IFERROR(E9*F9,0) -> 0 | J9: =IF(B9="","",IF(F9<=G9,"Reorder!","OK")) | K9: =IF(B9="","",SUMIFS('Order Tracker'!$G$3:$G$102,'Order Tracker'!$F$3:$F$102,B9)) | L9: =IF(B9="","",SUMIFS('Order Tracker'!$I$3:$I$102,'Order Tracker'!$F$3:$F$102,B9)) | M9: =IF(B9="","",RANK(L9,$L$3:$L$52)+COUNTIF($L$3:L9,L9)-1)
H10: =IFERROR(D10*F10,0) -> 0 | I10: =IFERROR(E10*F10,0) -> 0 | J10: =IF(B10="","",IF(F10<=G10,"Reorder!","OK")) | K10: =IF(B10="","",SUMIFS('Order Tracker'!$G$3:$G$102,'Order Tracker'!$F$3:$F$102,B10)) | L10: =IF(B10="","",SUMIFS('Order Tracker'!$I$3:$I$102,'Order Tracker'!$F$3:$F$102,B10)) | M10: =IF(B10="","",RANK(L10,$L$3:$L$52)+COUNTIF($L$3:L10,L10)-1)
H11: =IFERROR(D11*F11,0) -> 0 | I11: =IFERROR(E11*F11,0) -> 0 | J11: =IF(B11="","",IF(F11<=G11,"Reorder!","OK")) | K11: =IF(B11="","",SUMIFS('Order Tracker'!$G$3:$G$102,'Order Tracker'!$F$3:$F$102,B11)) | L11: =IF(B11="","",SUMIFS('Order Tracker'!$I$3:$I$102,'Order Tracker'!$F$3:$F$102,B11)) | M11: =IF(B11="","",RANK(L11,$L$3:$L$52)+COUNTIF($L$3:L11,L11)-1)
H12: =IFERROR(D12*F12,0) -> 0 | I12: =IFERROR(E12*F12,0) -> 0 | J12: =IF(B12="","",IF(F12<=G12,"Reorder!","OK")) | K12: =IF(B12="","",SUMIFS('Order Tracker'!$G$3:$G$102,'Order Tracker'!$F$3:$F$102,B12)) | L12: =IF(B12="","",SUMIFS('Order Tracker'!$I$3:$I$102,'Order Tracker'!$F$3:$F$102,B12)) | M12: =IF(B12="","",RANK(L12,$L$3:$L$52)+COUNTIF($L$3:L12,L12)-1)
H13: =IFERROR(D13*F13,0) -> 0 | I13: =IFERROR(E13*F13,0) -> 0 | J13: =IF(B13="","",IF(F13<=G13,"Reorder!","OK")) | K13: =IF(B13="","",SUMIFS('Order Tracker'!$G$3:$G$102,'Order Tracker'!$F$3:$F$102,B13)) | L13: =IF(B13="","",SUMIFS('Order Tracker'!$I$3:$I$102,'Order Tracker'!$F$3:$F$102,B13)) | M13: =IF(B13="","",RANK(L13,$L$3:$L$52)+COUNTIF($L$3:L13,L13)-1)
H14: =IFERROR(D14*F14,0) -> 0 | I14: =IFERROR(E14*F14,0) -> 0 | J14: =IF(B14="","",IF(F14<=G14,"Reorder!","OK")) | K14: =IF(B14="","",SUMIFS('Order Tracker'!$G$3:$G$102,'Order Tracker'!$F$3:$F$102,B14)) | L14: =IF(B14="","",SUMIFS('Order Tracker'!$I$3:$I$102,'Order Tracker'!$F$3:$F$102,B14)) | M14: =IF(B14="","",RANK(L14,$L$3:$L$52)+COUNTIF($L$3:L14,L14)-1)
... H52: =IFERROR(D52*F52,0) -> 0 | I52: =IFERROR(E52*F52,0) -> 0 | J52: =IF(B52="","",IF(F52<=G52,"Reorder!","OK")) | K52: =IF(B52="","",SUMIFS('Order Tracker'!$G$3:$G$102,'Order Tracker'!$F$3:$F$102,B52)) | L52: =IF(B52="","",SUMIFS('Order Tracker'!$I$3:$I$102,'Order Tracker'!$F$3:$F$102,B52)) | M52: =IF(B52="","",RANK(L52,$L$3:$L$52)+COUNTIF($L$3:L52,L52)-1)

Sheet Order Tracker
A1: {{CLIENT_NAME}} — Order Tracker
A2: Invoice # | B2: Line # | C2: Key | D2: Date | E2: Customer | F2: Product | G2: Qty | H2: Unit Price ({{CURRENCY}}) | I2: Line Total ({{CURRENCY}}) | J2: Order Status | K2: Payment Status | L2: Year | M2: Month
B3: =IF(A3="","",COUNTIF($A$3:A3,A3)) | C3: =IF(A3="","",A3&"-"&B3) | H3: =IF(F3="","",IFERROR(INDEX('Inventory Tracker'!$E$3:$E$52,MATCH(F3,'Inventory Tracker'!$B$3:$B$52,0)),0)) | I3: =IFERROR(G3*H3,0) -> 0 | L3: =IFERROR(YEAR(D3),"") -> 1899 | M3: =IFERROR(MONTH(D3),"") -> 12
B4: =IF(A4="","",COUNTIF($A$3:A4,A4)) | C4: =IF(A4="","",A4&"-"&B4) | H4: =IF(F4="","",IFERROR(INDEX('Inventory Tracker'!$E$3:$E$52,MATCH(F4,'Inventory Tracker'!$B$3:$B$52,0)),0)) | I4: =IFERROR(G4*H4,0) -> 0 | L4: =IFERROR(YEAR(D4),"") -> 1899 | M4: =IFERROR(MONTH(D4),"") -> 12
B5: =IF(A5="","",COUNTIF($A$3:A5,A5)) | C5: =IF(A5="","",A5&"-"&B5) | H5: =IF(F5="","",IFERROR(INDEX('Inventory Tracker'!$E$3:$E$52,MATCH(F5,'Inventory Tracker'!$B$3:$B$52,0)),0)) | I5: =IFERROR(G5*H5,0) -> 0 | L5: =IFERROR(YEAR(D5),"") -> 1899 | M5: =IFERROR(MONTH(D5),"") -> 12
B6: =IF(A6="","",COUNTIF($A$3:A6,A6)) | C6: =IF(A6="","",A6&"-"&B6) | H6: =IF(F6="","",IFERROR(INDEX('Inventory Tracker'!$E$3:$E$52,MATCH(F6,'Inventory Tracker'!$B$3:$B$52,0)),0)) | I6: =IFERROR(G6*H6,0) -> 0 | L6: =IFERROR(YEAR(D6),"") -> 1899 | M6: =IFERROR(MONTH(D6),"") -> 12
B7: =IF(A7="","",COUNTIF($A$3:A7,A7)) | C7: =IF(A7="","",A7&"-"&B7) | H7: =IF(F7="","",IFERROR(INDEX('Inventory Tracker'!$E$3:$E$52,MATCH(F7,'Inventory Tracker'!$B$3:$B$52,0)),0)) | I7: =IFERROR(G7*H7,0) -> 0 | L7: =IFERROR(YEAR(D7),"") -> 1899 | M7: =IFERROR(MONTH(D7),"") -> 12
B8: =IF(A8="","",COUNTIF($A$3:A8,A8)) | C8: =IF(A8="","",A8&"-"&B8) | H8: =IF(F8="","",IFERROR(INDEX('Inventory Tracker'!$E$3:$E$52,MATCH(F8,'Inventory Tracker'!$B$3:$B$52,0)),0)) | I8: =IFERROR(G8*H8,0) -> 0 | L8: =IFERROR(YEAR(D8),"") -> 1899 | M8: =IFERROR(MONTH(D8),"") -> 12
B9: =IF(A9="","",COUNTIF($A$3:A9,A9)) | C9: =IF(A9="","",A9&"-"&B9) | H9: =IF(F9="","",IFERROR(INDEX('Inventory Tracker'!$E$3:$E$52,MATCH(F9,'Inventory Tracker'!$B$3:$B$52,0)),0)) | I9: =IFERROR(G9*H9,0) -> 0 | L9: =IFERROR(YEAR(D9),"") -> 1899 | M9: =IFERROR(MONTH(D9),"") -> 12
B10: =IF(A10="","",COUNTIF($A$3:A10,A10)) | C10: =IF(A10="","",A10&"-"&B10) | H10: =IF(F10="","",IFERROR(INDEX('Inventory Tracker'!$E$3:$E$52,MATCH(F10,'Inventory Tracker'!$B$3:$B$52,0)),0)) | I10: =IFERROR(G10*H10,0) -> 0 | L10: =IFERROR(YEAR(D10),"") -> 1899 | M10: =IFERROR(MONTH(D10),"") -> 12
B11: =IF(A11="","",COUNTIF($A$3:A11,A11)) | C11: =IF(A11="","",A11&"-"&B11) | H11: =IF(F11="","",IFERROR(INDEX('Inventory Tracker'!$E$3:$E$52,MATCH(F11,'Inventory Tracker'!$B$3:$B$52,0)),0)) | I11: =IFERROR(G11*H11,0) -> 0 | L11: =IFERROR(YEAR(D11),"") -> 1899 | M11: =IFERROR(MONTH(D11),"") -> 12
B12: =IF(A12="","",COUNTIF($A$3:A12,A12)) | C12: =IF(A12="","",A12&"-"&B12) | H12: =IF(F12="","",IFERROR(INDEX('Inventory Tracker'!$E$3:$E$52,MATCH(F12,'Inventory Tracker'!$B$3:$B$52,0)),0)) | I12: =IFERROR(G12*H12,0) -> 0 | L12: =IFERROR(YEAR(D12),"") -> 1899 | M12: =IFERROR(MONTH(D12),"") -> 12
B13: =IF(A13="","",COUNTIF($A$3:A13,A13)) | C13: =IF(A13="","",A13&"-"&B13) | H13: =IF(F13="","",IFERROR(INDEX('Inventory Tracker'!$E$3:$E$52,MATCH(F13,'Inventory Tracker'!$B$3:$B$52,0)),0)) | I13: =IFERROR(G13*H13,0) -> 0 | L13: =IFERROR(YEAR(D13),"") -> 1899 | M13: =IFERROR(MONTH(D13),"") -> 12
B14: =IF(A14="","",COUNTIF($A$3:A14,A14)) | C14: =IF(A14="","",A14&"-"&B14) | H14: =IF(F14="","",IFERROR(INDEX('Inventory Tracker'!$E$3:$E$52,MATCH(F14,'Inventory Tracker'!$B$3:$B$52,0)),0)) | I14: =IFERROR(G14*H14,0) -> 0 | L14: =IFERROR(YEAR(D14),"") -> 1899 | M14: =IFERROR(MONTH(D14),"") -> 12
... B102: =IF(A102="","",COUNTIF($A$3:A102,A102)) | C102: =IF(A102="","",A102&"-"&B102) | H102: =IF(F102="","",IFERROR(INDEX('Inventory Tracker'!$E$3:$E$52,MATCH(F102,'Inventory Tracker'!$B$3:$B$52,0)),0)) | I102: =IFERROR(G102*H102,0) -> 0 | L102: =IFERROR(YEAR(D102),"") -> 1899 | M102: =IFERROR(MONTH(D102),"") -> 12

Sheet Invoice Generator
A1: {{CLIENT_NAME}}
A2: ="{{NICHE}} | "&Setup!$B$4 -> {{NICHE}} | hello@example.com
E4: Enter Invoice # | F4: 1001
A5: Bill To: | E5: Displayed As | F5: =Setup!$B$6&F4 -> INV-1001
A6: =IFERROR(INDEX('Order Tracker'!$E$3:$E$102,MATCH($F$4&"-1",'Order Tracker'!$C$3:$C$102,0)),"")
A7: Date: | B7: =IFERROR(INDEX('Order Tracker'!$D$3:$D$102,MATCH($F$4&"-1",'Order Tracker'!$C$3:$C$102,0)),"")
A8: Order Status: | B8: =IFERROR(INDEX('Order Tracker'!$J$3:$J$102,MATCH($F$4&"-1",'Order Tracker'!$C$3:$C$102,0)),"")
A9: Payment Status: | B9: =IFERROR(INDEX('Order Tracker'!$K$3:$K$102,MATCH($F$4&"-1",'Order Tracker'!$C$3:$C$102,0)),"")
A11: Product | B11: Qty | C11: Unit Price ({{CURRENCY}}) | D11: Line Total ({{CURRENCY}})
A12: =IFERROR(INDEX('Order Tracker'!$F$3:$F$102,MATCH($F$4&"-"&1,'Order Tracker'!$C$3:$C$102,0)),"") | B12: =IFERROR(INDEX('Order Tracker'!$G$3:$G$102,MATCH($F$4&"-"&1,'Order Tracker'!$C$3:$C$102,0)),"") | C12: =IFERROR(INDEX('Order Tracker'!$H$3:$H$102,MATCH($F$4&"-"&1,'Order Tracker'!$C$3:$C$102,0)),"") | D12: =IFERROR(INDEX('Order Tracker'!$I$3:$I$102,MATCH($F$4&"-"&1,'Order Tracker'!$C$3:$C$102,0)),"")
A13: =IFERROR(INDEX('Order Tracker'!$F$3:$F$102,MATCH($F$4&"-"&2,'Order Tracker'!$C$3:$C$102,0)),"") | B13: =IFERROR(INDEX('Order Tracker'!$G$3:$G$102,MATCH($F$4&"-"&2,'Order Tracker'!$C$3:$C$102,0)),"") | C13: =IFERROR(INDEX('Order Tracker'!$H$3:$H$102,MATCH($F$4&"-"&2,'Order Tracker'!$C$3:$C$102,0)),"") | D13: =IFERROR(INDEX('Order Tracker'!$I$3:$I$102,MATCH($F$4&"-"&2,'Order Tracker'!$C$3:$C$102,0)),"")
A14: =IFERROR(INDEX('Order Tracker'!$F$3:$F$102,MATCH($F$4&"-"&3,'Order Tracker'!$C$3:$C$102,0)),"") | B14: =IFERROR(INDEX('Order Tracker'!$G$3:$G$102,MATCH($F$4&"-"&3,'Order Tracker'!$C$3:$C$102,0)),"") | C14: =IFERROR(INDEX('Order Tracker'!$H$3:$H$102,MATCH($F$4&"-"&3,'Order Tracker'!$C$3:$C$102,0)),"") | D14: =IFERROR(INDEX('Order Tracker'!$I$3:$I$102,MATCH($F$4&"-"&3,'Order Tracker'!$C$3:$C$102,0)),"")
A15: =IFERROR(INDEX('Order Tracker'!$F$3:$F$102,MATCH($F$4&"-"&4,'Order Tracker'!$C$3:$C$102,0)),"") | B15: =IFERROR(INDEX('Order Tracker'!$G$3:$G$102,MATCH($F$4&"-"&4,'Order Tracker'!$C$3:$C$102,0)),"") | C15: =IFERROR(INDEX('Order Tracker'!$H$3:$H$102,MATCH($F$4&"-"&4,'Order Tracker'!$C$3:$C$102,0)),"") | D15: =IFERROR(INDEX('Order Tracker'!$I$3:$I$102,MATCH($F$4&"-"&4,'Order Tracker'!$C$3:$C$102,0)),"")
A16: =IFERROR(INDEX('Order Tracker'!$F$3:$F$102,MATCH($F$4&"-"&5,'Order Tracker'!$C$3:$C$102,0)),"") | B16: =IFERROR(INDEX('Order Tracker'!$G$3:$G$102,MATCH($F$4&"-"&5,'Order Tracker'!$C$3:$C$102,0)),"") | C16: =IFERROR(INDEX('Order Tracker'!$H$3:$H$102,MATCH($F$4&"-"&5,'Order Tracker'!$C$3:$C$102,0)),"") | D16: =IFERROR(INDEX('Order Tracker'!$I$3:$I$102,MATCH($F$4&"-"&5,'Order Tracker'!$C$3:$C$102,0)),"")
A17: =IFERROR(INDEX('Order Tracker'!$F$3:$F$102,MATCH($F$4&"-"&6,'Order Tracker'!$C$3:$C$102,0)),"") | B17: =IFERROR(INDEX('Order Tracker'!$G$3:$G$102,MATCH($F$4&"-"&6,'Order Tracker'!$C$3:$C$102,0)),"") | C17: =IFERROR(INDEX('Order Tracker'!$H$3:$H$102,MATCH($F$4&"-"&6,'Order Tracker'!$C$3:$C$102,0)),"") | D17: =IFERROR(INDEX('Order Tracker'!$I$3:$I$102,MATCH($F$4&"-"&6,'Order Tracker'!$C$3:$C$102,0)),"")
A18: =IFERROR(INDEX('Order Tracker'!$F$3:$F$102,MATCH($F$4&"-"&7,'Order Tracker'!$C$3:$C$102,0)),"") | B18: =IFERROR(INDEX('Order Tracker'!$G$3:$G$102,MATCH($F$4&"-"&7,'Order Tracker'!$C$3:$C$102,0)),"") | C18: =IFERROR(INDEX('Order Tracker'!$H$3:$H$102,MATCH($F$4&"-"&7,'Order Tracker'!$C$3:$C$102,0)),"") | D18: =IFERROR(INDEX('Order Tracker'!$I$3:$I$102,MATCH($F$4&"-"&7,'Order Tracker'!$C$3:$C$102,0)),"")
A19: =IFERROR(INDEX('Order Tracker'!$F$3:$F$102,MATCH($F$4&"-"&8,'Order Tracker'!$C$3:$C$102,0)),"") | B19: =IFERROR(INDEX('Order Tracker'!$G$3:$G$102,MATCH($F$4&"-"&8,'Order Tracker'!$C$3:$C$102,0)),"") | C19: =IFERROR(INDEX('Order Tracker'!$H$3:$H$102,MATCH($F$4&"-"&8,'Order Tracker'!$C$3:$C$102,0)),"") | D19: =IFERROR(INDEX('Order Tracker'!$I$3:$I$102,MATCH($F$4&"-"&8,'Order Tracker'!$C$3:$C$102,0)),"")
A20: =IFERROR(INDEX('Order Tracker'!$F$3:$F$102,MATCH($F$4&"-"&9,'Order Tracker'!$C$3:$C$102,0)),"") | B20: =IFERROR(INDEX('Order Tracker'!$G$3:$G$102,MATCH($F$4&"-"&9,'Order Tracker'!$C$3:$C$102,0)),"") | C20: =IFERROR(INDEX('Order Tracker'!$H$3:$H$102,MATCH($F$4&"-"&9,'Order Tracker'!$C$3:$C$102,0)),"") | D20: =IFERROR(INDEX('Order Tracker'!$I$3:$I$102,MATCH($F$4&"-"&9,'Order Tracker'!$C$3:$C$102,0)),"")
A21: =IFERROR(INDEX('Order Tracker'!$F$3:$F$102,MATCH($F$4&"-"&10,'Order Tracker'!$C$3:$C$102,0)),"") | B21: =IFERROR(INDEX('Order Tracker'!$G$3:$G$102,MATCH($F$4&"-"&10,'Order Tracker'!$C$3:$C$102,0)),"") | C21: =IFERROR(INDEX('Order Tracker'!$H$3:$H$102,MATCH($F$4&"-"&10,'Order Tracker'!$C$3:$C$102,0)),"") | D21: =IFERROR(INDEX('Order Tracker'!$I$3:$I$102,MATCH($F$4&"-"&10,'Order Tracker'!$C$3:$C$102,0)),"")
C23: Subtotal: | D23: =SUM(D12:D21) -> 0
C24: Tax: | D24: =D23*Setup!$B$5 -> 0
C25: Total Due: | D25: =D23+D24 -> 0
A27: Change the 'Enter Invoice #' cell above to generate an invoice for any order on file.

Sheet Sales Dashboard
A1: {{CLIENT_NAME}} — Sales Dashboard
A2: {{NICHE}} — figures in {{CURRENCY}}
A5: Total Orders | B5: Total Revenue ({{CURRENCY}}) | C5: Total Customers | D5: Avg Order Value ({{CURRENCY}})
A6: =SUMPRODUCT(('Order Tracker'!$B$3:$B$102=1)*1) -> 0 | B6: =SUM('Order Tracker'!$I$3:$I$102) -> 0 | C6: =COUNTA('Customer Tracker'!$B$3:$B$52) -> 0 | D6: =IFERROR(B6/A6,0) -> 0
A9: Orders by Status
A10: Status | B10: Orders
A11: Pending | B11: =COUNTIFS('Order Tracker'!$J$3:$J$102,"Pending",'Order Tracker'!$B$3:$B$102,1) -> 0
A12: In Production | B12: =COUNTIFS('Order Tracker'!$J$3:$J$102,"In Production",'Order Tracker'!$B$3:$B$102,1) -> 0
A13: Shipped | B13: =COUNTIFS('Order Tracker'!$J$3:$J$102,"Shipped",'Order Tracker'!$B$3:$B$102,1) -> 0
A14: Delivered | B14: =COUNTIFS('Order Tracker'!$J$3:$J$102,"Delivered",'Order Tracker'!$B$3:$B$102,1) -> 0
A15: Cancelled | B15: =COUNTIFS('Order Tracker'!$J$3:$J$102,"Cancelled",'Order Tracker'!$B$3:$B$102,1) -> 0
A18: Revenue by Month | C18: Year | D18: 2026
A19: Month | B19: Revenue
A20: Jan | B20: =SUMIFS('Order Tracker'!$I$3:$I$102,'Order Tracker'!$L$3:$L$102,$D$18,'Order Tracker'!$M$3:$M$102,1) -> 0
A21: Feb | B21: =SUMIFS('Order Tracker'!$I$3:$I$102,'Order Tracker'!$L$3:$L$102,$D$18,'Order Tracker'!$M$3:$M$102,2) -> 0
A22: Mar | B22: =SUMIFS('Order Tracker'!$I$3:$I$102,'Order Tracker'!$L$3:$L$102,$D$18,'Order Tracker'!$M$3:$M$102,3) -> 0
A23: Apr | B23: =SUMIFS('Order Tracker'!$I$3:$I$102,'Order Tracker'!$L$3:$L$102,$D$18,'Order Tracker'!$M$3:$M$102,4) -> 0
A24: May | B24: =SUMIFS('Order Tracker'!$I$3:$I$102,'Order Tracker'!$L$3:$L$102,$D$18,'Order Tracker'!$M$3:$M$102,5) -> 0
A25: Jun | B25: =SUMIFS('Order Tracker'!$I$3:$I$102,'Order Tracker'!$L$3:$L$102,$D$18,'Order Tracker'!$M$3:$M$102,6) -> 0
A26: Jul | B26: =SUMIFS('Order Tracker'!$I$3:$I$102,'Order Tracker'!$L$3:$L$102,$D$18,'Order Tracker'!$M$3:$M$102,7) -> 0
A27: Aug | B27: =SUMIFS('Order Tracker'!$I$3:$I$102,'Order Tracker'!$L$3:$L$102,$D$18,'Order Tracker'!$M$3:$M$102,8) -> 0
A28: Sep | B28: =SUMIFS('Order Tracker'!$I$3:$I$102,'Order Tracker'!$L$3:$L$102,$D$18,'Order Tracker'!$M$3:$M$102,9) -> 0
A29: Oct | B29: =SUMIFS('Order Tracker'!$I$3:$I$102,'Order Tracker'!$L$3:$L$102,$D$18,'Order Tracker'!$M$3:$M$102,10) -> 0
A30: Nov | B30: =SUMIFS('Order Tracker'!$I$3:$I$102,'Order Tracker'!$L$3:$L$102,$D$18,'Order Tracker'!$M$3:$M$102,11) -> 0
A31: Dec | B31: =SUMIFS('Order Tracker'!$I$3:$I$102,'Order Tracker'!$L$3:$L$102,$D$18,'Order Tracker'!$M$3:$M$102,12) -> 0
A34: Top 5 Products by Revenue
A35: Rank | B35: Product | C35: Revenue
A36: 1 | B36: =IFERROR(INDEX('Inventory Tracker'!$B$3:$B$52,MATCH(1,'Inventory Tracker'!$M$3:$M$52,0)),"") | C36: =IFERROR(INDEX('Inventory Tracker'!$L$3:$L$52,MATCH(1,'Inventory Tracker'!$M$3:$M$52,0)),"")
A37: 2 | B37: =IFERROR(INDEX('Inventory Tracker'!$B$3:$B$52,MATCH(2,'Inventory Tracker'!$M$3:$M$52,0)),"") | C37: =IFERROR(INDEX('Inventory Tracker'!$L$3:$L$52,MATCH(2,'Inventory Tracker'!$M$3:$M$52,0)),"")
A38: 3 | B38: =IFERROR(INDEX('Inventory Tracker'!$B$3:$B$52,MATCH(3,'Inventory Tracker'!$M$3:$M$52,0)),"") | C38: =IFERROR(INDEX('Inventory Tracker'!$L$3:$L$52,MATCH(3,'Inventory Tracker'!$M$3:$M$52,0)),"")
A39: 4 | B39: =IFERROR(INDEX('Inventory Tracker'!$B$3:$B$52,MATCH(4,'Inventory Tracker'!$M$3:$M$52,0)),"") | C39: =IFERROR(INDEX('Inventory Tracker'!$L$3:$L$52,MATCH(4,'Inventory Tracker'!$M$3:$M$52,0)),"")
A40: 5 | B40: =IFERROR(INDEX('Inventory Tracker'!$B$3:$B$52,MATCH(5,'Inventory Tracker'!$M$3:$M$52,0)),"") | C40: =IFERROR(INDEX('Inventory Tracker'!$L$3:$L$52,MATCH(5,'Inventory Tracker'!$M$3:$M$52,0)),"")

Sheet Customer Insights
A1: {{CLIENT_NAME}} — Customer Insights
A2: {{NICHE}} — figures in {{CURRENCY}}
A5: Total Customers | B5: Returning Customers | C5: Repeat Customer Rate | D5: Avg Spend per Customer ({{CURRENCY}})
A6: =COUNTA('Customer Tracker'!$B$3:$B$52) -> 0 | B6: =COUNTIFS('Customer Tracker'!$F$3:$F$52,">1") -> 0 | C6: =IFERROR(B6/A6,0) -> 0 | D6: =IFERROR(AVERAGE('Customer Tracker'!$G$3:$G$52),0) -> 0
A9: Top 10 Customers by Spend
A10: Rank | B10: Customer | C10: Total Spent | D10: Total Orders
A11: 1 | B11: =IFERROR(INDEX('Customer Tracker'!$B$3:$B$52,MATCH(1,'Customer Tracker'!$K$3:$K$52,0)),"") | C11: =IFERROR(INDEX('Customer Tracker'!$G$3:$G$52,MATCH(1,'Customer Tracker'!$K$3:$K$52,0)),"") | D11: =IFERROR(INDEX('Customer Tracker'!$F$3:$F$52,MATCH(1,'Customer Tracker'!$K$3:$K$52,0)),"")
A12: 2 | B12: =IFERROR(INDEX('Customer Tracker'!$B$3:$B$52,MATCH(2,'Customer Tracker'!$K$3:$K$52,0)),"") | C12: =IFERROR(INDEX('Customer Tracker'!$G$3:$G$52,MATCH(2,'Customer Tracker'!$K$3:$K$52,0)),"") | D12: =IFERROR(INDEX('Customer Tracker'!$F$3:$F$52,MATCH(2,'Customer Tracker'!$K$3:$K$52,0)),"")
A13: 3 | B13: =IFERROR(INDEX('Customer Tracker'!$B$3:$B$52,MATCH(3,'Customer Tracker'!$K$3:$K$52,0)),"") | C13: =IFERROR(INDEX('Customer Tracker'!$G$3:$G$52,MATCH(3,'Customer Tracker'!$K$3:$K$52,0)),"") | D13: =IFERROR(INDEX('Customer Tracker'!$F$3:$F$52,MATCH(3,'Customer Tracker'!$K$3:$K$52,0)),"")
A14: 4 | B14: =IFERROR(INDEX('Customer Tracker'!$B$3:$B$52,MATCH(4,'Customer Tracker'!$K$3:$K$52,0)),"") | C14: =IFERROR(INDEX('Customer Tracker'!$G$3:$G$52,MATCH(4,'Customer Tracker'!$K$3:$K$52,0)),"") | D14: =IFERROR(INDEX('Customer Tracker'!$F$3:$F$52,MATCH(4,'Customer Tracker'!$K$3:$K$52,0)),"")
A15: 5 | B15: =IFERROR(INDEX('Customer Tracker'!$B$3:$B$52,MATCH(5,'Customer Tracker'!$K$3:$K$52,0)),"") | C15: =IFERROR(INDEX('Customer Tracker'!$G$3:$G$52,MATCH(5,'Customer Tracker'!$K$3:$K$52,0)),"") | D15: =IFERROR(INDEX('Customer Tracker'!$F$3:$F$52,MATCH(5,'Customer Tracker'!$K$3:$K$52,0)),"")
A16: 6 | B16: =IFERROR(INDEX('Customer Tracker'!$B$3:$B$52,MATCH(6,'Customer Tracker'!$K$3:$K$52,0)),"") | C16: =IFERROR(INDEX('Customer Tracker'!$G$3:$G$52,MATCH(6,'Customer Tracker'!$K$3:$K$52,0)),"") | D16: =IFERROR(INDEX('Customer Tracker'!$F$3:$F$52,MATCH(6,'Customer Tracker'!$K$3:$K$52,0)),"")
A17: 7 | B17: =IFERROR(INDEX('Customer Tracker'!$B$3:$B$52,MATCH(7,'Customer Tracker'!$K$3:$K$52,0)),"") | C17: =IFERROR(INDEX('Customer Tracker'!$G$3:$G$52,MATCH(7,'Customer Tracker'!$K$3:$K$52,0)),"") | D17: =IFERROR(INDEX('Customer Tracker'!$F$3:$F$52,MATCH(7,'Customer Tracker'!$K$3:$K$52,0)),"")
A18: 8 | B18: =IFERROR(INDEX('Customer Tracker'!$B$3:$B$52,MATCH(8,'Customer Tracker'!$K$3:$K$52,0)),"") | C18: =IFERROR(INDEX('Customer Tracker'!$G$3:$G$52,MATCH(8,'Customer Tracker'!$K$3:$K$52,0)),"") | D18: =IFERROR(INDEX('Customer Tracker'!$F$3:$F$52,MATCH(8,'Customer Tracker'!$K$3:$K$52,0)),"")
A19: 9 | B19: =IFERROR(INDEX('Customer Tracker'!$B$3:$B$52,MATCH(9,'Customer Tracker'!$K$3:$K$52,0)),"") | C19: =IFERROR(INDEX('Customer Tracker'!$G$3:$G$52,MATCH(9,'Customer Tracker'!$K$3:$K$52,0)),"") | D19: =IFERROR(INDEX('Customer Tracker'!$F$3:$F$52,MATCH(9,'Customer Tracker'!$K$3:$K$52,0)),"")
A20: 10 | B20: =IFERROR(INDEX('Customer Tracker'!$B$3:$B$52,MATCH(10,'Customer Tracker'!$K$3:$K$52,0)),"") | C20: =IFERROR(INDEX('Customer Tracker'!$G$3:$G$52,MATCH(10,'Customer Tracker'!$K$3:$K$52,0)),"") | D20: =IFERROR(INDEX('Customer Tracker'!$F$3:$F$52,MATCH(10,'Customer Tracker'!$K$3:$K$52,0)),"")

Sheet Notes & Legend
A1: Notes & Legend
A3: Color / Style | B3: Meaning
A4: Yellow cells | B4: Input cells — change these (Year, Invoice #, Tax Rate).
A5: White cells with borders | B5: Data entry rows in Customer Tracker, Inventory Tracker, and Order Tracker.
A6: Green header cells | B6: Column headers — do not edit.
A7: Black formula cells | B7: Calculated automatically — do not overwrite (Unit Price, Line Total, Rank, etc.).
A8: Light red rows (Inventory Tracker) | B8: Products at or below their Reorder Level.
A9: Light green / yellow / light red rows (Order Tracker) | B9: Delivered / Pending / Cancelled orders, color-coded automatically.
A11: Prepared for {{CLIENT_NAME}} ({{NICHE}}). Amounts are in {{CURRENCY}}.
